{
 "301": {
  "total": 180,
  "list": [
   {
    "uid": "700367142",
    "gacha_type": "301",
    "item_id": "",
    "count": "1",
    "time": "2021-11-21 08:17:11",
    "name": "Thrilling Tales of Dragon Slayers",
    "lang": "en-us",
    "item_type": "Weapon",
    "rank_type": "3",
    "id": "1637478360000027263"
   },
   {
    "uid": "700367142",
    "gacha_type": "301",
    "item_id": "",
    "count": "1",
    "time": "2021-11-19 19:37:02",
    "name": "Raven Bow",
    "lang": "en-us",
    "item_type": "Weapon",
    "rank_type": "3",
    "id": "1637345160000161379"
   },
   {
    "uid": "700367142",
    "gacha_type": "301",
    "item_id": "",
    "count": "1",
    "time": "2021-11-19 19:36:55",
    "name": "Thrilling Tales of Dragon Slayers",
    "lang": "en-us",
    "item_type": "Weapon",
    "rank_type": "3",
    "id": "1637345160000160860"
   },
   {
    "uid": "700367142",
    "gacha_type": "301",
    "item_id": "",
    "count": "1",
    "time": "2021-11-19 19:36:16",
    "name": "Sayu",
    "lang": "en-us",
    "item_type": "Character",
    "rank_type": "4",
    "id": "1637345160000158142"
   },
   {
    "uid": "700367142",
    "gacha_type": "301",
    "item_id": "",
    "count": "1",
    "time": "2021-11-19 19:36:06",
    "name": "Sharpshooter's Oath",
    "lang": "en-us",
    "item_type": "Weapon",
    "rank_type": "3",
    "id": "1637345160000157515"
   },
   {
    "uid": "700367142",
    "gacha_type": "301",
    "item_id": "",
    "count": "1",
    "time": "2021-11-19 19:35:58",
    "name": "Slingshot",
    "lang": "en-us",
    "item_type": "Weapon",
    "rank_type": "3",
    "id": "1637345160000156973"
   },
   {
    "uid": "700367142",
    "gacha_type": "301",
    "item_id": "",
    "count": "1",
    "time": "2021-11-14 10:28:23",
    "name": "Bloodtainted Greatsword",
    "lang": "en-us",
    "item_type": "Weapon",
    "rank_type": "3",
    "id": "1636880760000106728"
   },
   {
    "uid": "700367142",
    "gacha_type": "301",
    "item_id": "",
    "count": "1",
    "time": "2021-11-02 18:22:25",
    "name": "Bloodtainted Greatsword",
    "lang": "en-us",
    "item_type": "Weapon",
    "rank_type": "3",
    "id": "1635872760027499496"
   },
   {
    "uid": "700367142",
    "gacha_type": "301",
    "item_id": "",
    "count": "1",
    "time": "2021-11-02 18:22:20",
    "name": "Sharpshooter's Oath",
    "lang": "en-us",
    "item_type": "Weapon",
    "rank_type": "3",
    "id": "1635872760027450322"
   },
   {
    "uid": "700367142",
    "gacha_type": "301",
    "item_id": "",
    "count": "1",
    "time": "2021-11-02 18:22:16",
    "name": "Cool Steel",
    "lang": "en-us",
    "item_type": "Weapon",
    "rank_type": "3",
    "id": "1635872760027411686"
   },
   {
    "uid": "700367142",
    "gacha_type": "301",
    "item_id": "",
    "count": "1",
    "time": "2021-11-02 18:22:11",
    "name": "Harbinger of Dawn",
    "lang": "en-us",
    "item_type": "Weapon",
    "rank_type": "3",
    "id": "1635872760027361855"
   },
   {
    "uid": "700367142",
    "gacha_type": "301",
    "item_id": "",
    "count": "1",
    "time": "2021-11-02 18:22:06",
    "name": "Ferrous Shadow",
    "lang": "en-us",
    "item_type": "Weapon",
    "rank_type": "3",
    "id": "1635872760027311372"
   },
   {
    "uid": "700367142",
    "gacha_type": "301",
    "item_id": "",
    "count": "1",
    "time": "2021-11-02 18:22:01",
    "name": "Skyrider Sword",
    "lang": "en-us",
    "item_type": "Weapon",
    "rank_type": "3",
    "id": "1635872760027261927"
   },
   {
    "uid": "700367142",
    "gacha_type": "301",
    "item_id": "",
    "count": "1",
    "time": "2021-11-02 18:21:52",
    "name": "Sayu",
    "lang": "en-us",
    "item_type": "Character",
    "rank_type": "4",
    "id": "1635872760027171767"
   },
   {
    "uid": "700367142",
    "gacha_type": "301",
    "item_id": "",
    "count": "1",
    "time": "2021-09-30 21:04:45",
    "name": "Cool Steel",
    "lang": "en-us",
    "item_type": "Weapon",
    "rank_type": "3",
    "id": "1633032360000033609"
   },
   {
    "uid": "700367142",
    "gacha_type": "301",
    "item_id": "",
    "count": "1",
    "time": "2021-09-30 21:04:35",
    "name": "Thrilling Tales of Dragon Slayers",
    "lang": "en-us",
    "item_type": "Weapon",
    "rank_type": "3",
    "id": "1633032360000032363"
   },
   {
    "uid": "700367142",
    "gacha_type": "301",
    "item_id": "",
    "count": "1",
    "time": "2021-09-30 21:04:28",
    "name": "Bloodtainted Greatsword",
    "lang": "en-us",
    "item_type": "Weapon",
    "rank_type": "3",
    "id": "1633032360000031468"
   },
   {
    "uid": "700367142",
    "gacha_type": "301",
    "item_id": "",
    "count": "1",
    "time": "2021-09-30 21:04:22",
    "name": "Black Tassel",
    "lang": "en-us",
    "item_type": "Weapon",
    "rank_type": "3",
    "id": "1633032360000030832"
   },
   {
    "uid": "700367142",
    "gacha_type": "301",
    "item_id": "",
    "count": "1",
    "time": "2021-09-23 10:28:19",
    "name": "Harbinger of Dawn",
    "lang": "en-us",
    "item_type": "Weapon",
    "rank_type": "3",
    "id": "1632387960000082892"
   },
   {
    "uid": "700367142",
    "gacha_type": "301",
    "item_id": "",
    "count": "1",
    "time": "2021-09-21 05:46:48",
    "name": "Black Tassel",
    "lang": "en-us",
    "item_type": "Weapon",
    "rank_type": "3",
    "id": "1632197160000057344"
   },
   {
    "uid": "700367142",
    "gacha_type": "301",
    "item_id": "",
    "count": "1",
    "time": "2021-09-18 20:48:16",
    "name": "Cool Steel",
    "lang": "en-us",
    "item_type": "Weapon",
    "rank_type": "3",
    "id": "1631991960000275262"
   },
   {
    "uid": "700367142",
    "gacha_type": "301",
    "item_id": "",
    "count": "1",
    "time": "2021-09-18 20:48:08",
    "name": "Emerald Orb",
    "lang": "en-us",
    "item_type": "Weapon",
    "rank_type": "3",
    "id": "1631991960000274508"
   },
   {
    "uid": "700367142",
    "gacha_type": "301",
    "item_id": "",
    "count": "1",
    "time": "2021-09-17 14:18:39",
    "name": "Sharpshooter's Oath",
    "lang": "en-us",
    "item_type": "Weapon",
    "rank_type": "3",
    "id": "1631883960000120180"
   },
   {
    "uid": "700367142",
    "gacha_type": "301",
    "item_id": "",
    "count": "1",
    "time": "2021-09-17 11:22:45",
    "name": "Xiangling",
    "lang": "en-us",
    "item_type": "Character",
    "rank_type": "4",
    "id": "1631873160000124165"
   },
   {
    "uid": "700367142",
    "gacha_type": "301",
    "item_id": "",
    "count": "1",
    "time": "2021-09-17 11:22:37",
    "name": "Emerald Orb",
    "lang": "en-us",
    "item_type": "Weapon",
    "rank_type": "3",
    "id": "1631873160000123461"
   },
   {
    "uid": "700367142",
    "gacha_type": "301",
    "item_id": "",
    "count": "1",
    "time": "2021-09-15 19:04:10",
    "name": "Emerald Orb",
    "lang": "en-us",
    "item_type": "Weapon",
    "rank_type": "3",
    "id": "1631729160000094725"
   },
   {
    "uid": "700367142",
    "gacha_type": "301",
    "item_id": "",
    "count": "1",
    "time": "2021-09-14 06:53:02",
    "name": "Black Tassel",
    "lang": "en-us",
    "item_type": "Weapon",
    "rank_type": "3",
    "id": "1631595960000087363"
   },
   {
    "uid": "700367142",
    "gacha_type": "301",
    "item_id": "",
    "count": "1",
    "time": "2021-09-13 20:59:32",
    "name": "Skyrider Sword",
    "lang": "en-us",
    "item_type": "Weapon",
    "rank_type": "3",
    "id": "1631559960000353405"
   },
   {
    "uid": "700367142",
    "gacha_type": "301",
    "item_id": "",
    "count": "1",
    "time": "2021-09-12 07:54:29",
    "name": "Slingshot",
    "lang": "en-us",
    "item_type": "Weapon",
    "rank_type": "3",
    "id": "1631426760000151192"
   },
   {
    "uid": "700367142",
    "gacha_type": "301",
    "item_id": "",
    "count": "1",
    "time": "2021-09-10 20:08:31",
    "name": "Bloodtainted Greatsword",
    "lang": "en-us",
    "item_type": "Weapon",
    "rank_type": "3",
    "id": "1631300760000070250"
   },
   {
    "uid": "700367142",
    "gacha_type": "301",
    "item_id": "",
    "count": "1",
    "time": "2021-09-09 18:53:38",
    "name": "Bloodtainted Greatsword",
    "lang": "en-us",
    "item_type": "Weapon",
    "rank_type": "3",
    "id": "1631207160000511414"
   },
   {
    "uid": "700367142",
    "gacha_type": "301",
    "item_id": "",
    "count": "1",
    "time": "2021-09-09 18:53:30",
    "name": "Magic Guide",
    "lang": "en-us",
    "item_type": "Weapon",
    "rank_type": "3",
    "id": "1631207160000510021"
   },
   {
    "uid": "700367142",
    "gacha_type": "301",
    "item_id": "",
    "count": "1",
    "time": "2021-09-08 18:41:09",
    "name": "Debate Club",
    "lang": "en-us",
    "item_type": "Weapon",
    "rank_type": "3",
    "id": "1631120760000298623"
   },
   {
    "uid": "700367142",
    "gacha_type": "301",
    "item_id": "",
    "count": "1",
    "time": "2021-09-08 18:40:51",
    "name": "Lion's Roar",
    "lang": "en-us",
    "item_type": "Weapon",
    "rank_type": "4",
    "id": "1631120760000296488"
   },
   {
    "uid": "700367142",
    "gacha_type": "301",
    "item_id": "",
    "count": "1",
    "time": "2021-09-06 18:11:51",
    "name": "Slingshot",
    "lang": "en-us",
    "item_type": "Weapon",
    "rank_type": "3",
    "id": "1630947960000103074"
   },
   {
    "uid": "700367142",
    "gacha_type": "301",
    "item_id": "",
    "count": "1",
    "time": "2021-09-06 16:27:19",
    "name": "Sucrose",
    "lang": "en-us",
    "item_type": "Character",
    "rank_type": "4",
    "id": "1630940760000227710"
   },
   {
    "uid": "700367142",
    "gacha_type": "301",
    "item_id": "",
    "count": "1",
    "time": "2021-09-05 18:54:25",
    "name": "Ferrous Shadow",
    "lang": "en-us",
    "item_type": "Weapon",
    "rank_type": "3",
    "id": "1630861560000500201"
   },
   {
    "uid": "700367142",
    "gacha_type": "301",
    "item_id": "",
    "count": "1",
    "time": "2021-09-05 18:54:17",
    "name": "Ferrous Shadow",
    "lang": "en-us",
    "item_type": "Weapon",
    "rank_type": "3",
    "id": "1630861560000498886"
   },
   {
    "uid": "700367142",
    "gacha_type": "301",
    "item_id": "",
    "count": "1",
    "time": "2021-09-05 18:53:24",
    "name": "Jean",
    "lang": "en-us",
    "item_type": "Character",
    "rank_type": "5",
    "id": "1630861560000490994"
   },
   {
    "uid": "700367142",
    "gacha_type": "301",
    "item_id": "",
    "count": "1",
    "time": "2021-09-05 07:45:17",
    "name": "Debate Club",
    "lang": "en-us",
    "item_type": "Weapon",
    "rank_type": "3",
    "id": "1630821960000153765"
   },
   {
    "uid": "700367142",
    "gacha_type": "301",
    "item_id": "",
    "count": "1",
    "time": "2021-09-05 07:45:10",
    "name": "Skyrider Sword",
    "lang": "en-us",
    "item_type": "Weapon",
    "rank_type": "3",
    "id": "1630821960000153370"
   },
   {
    "uid": "700367142",
    "gacha_type": "301",
    "item_id": "",
    "count": "1",
    "time": "2021-09-05 07:39:24",
    "name": "Cool Steel",
    "lang": "en-us",
    "item_type": "Weapon",
    "rank_type": "3",
    "id": "1630821960000131398"
   },
   {
    "uid": "700367142",
    "gacha_type": "301",
    "item_id": "",
    "count": "1",
    "time": "2021-09-05 07:39:24",
    "name": "Sayu",
    "lang": "en-us",
    "item_type": "Character",
    "rank_type": "4",
    "id": "1630821960000131397"
   },
   {
    "uid": "700367142",
    "gacha_type": "301",
    "item_id": "",
    "count": "1",
    "time": "2021-09-05 07:39:24",
    "name": "Sucrose",
    "lang": "en-us",
    "item_type": "Character",
    "rank_type": "4",
    "id": "1630821960000131396"
   },
   {
    "uid": "700367142",
    "gacha_type": "301",
    "item_id": "",
    "count": "1",
    "time": "2021-09-05 07:39:24",
    "name": "Skyrider Sword",
    "lang": "en-us",
    "item_type": "Weapon",
    "rank_type": "3",
    "id": "1630821960000131395"
   },
   {
    "uid": "700367142",
    "gacha_type": "301",
    "item_id": "",
    "count": "1",
    "time": "2021-09-05 07:39:24",
    "name": "Slingshot",
    "lang": "en-us",
    "item_type": "Weapon",
    "rank_type": "3",
    "id": "1630821960000131394"
   },
   {
    "uid": "700367142",
    "gacha_type": "301",
    "item_id": "",
    "count": "1",
    "time": "2021-09-05 07:39:24",
    "name": "Skyrider Sword",
    "lang": "en-us",
    "item_type": "Weapon",
    "rank_type": "3",
    "id": "1630821960000131393"
   },
   {
    "uid": "700367142",
    "gacha_type": "301",
    "item_id": "",
    "count": "1",
    "time": "2021-09-05 07:39:24",
    "name": "Cool Steel",
    "lang": "en-us",
    "item_type": "Weapon",
    "rank_type": "3",
    "id": "1630821960000131392"
   },
   {
    "uid": "700367142",
    "gacha_type": "301",
    "item_id": "",
    "count": "1",
    "time": "2021-09-05 07:39:24",
    "name": "Black Tassel",
    "lang": "en-us",
    "item_type": "Weapon",
    "rank_type": "3",
    "id": "1630821960000131391"
   },
   {
    "uid": "700367142",
    "gacha_type": "301",
    "item_id": "",
    "count": "1",
    "time": "2021-09-05 07:39:24",
    "name": "Debate Club",
    "lang": "en-us",
    "item_type": "Weapon",
    "rank_type": "3",
    "id": "1630821960000131390"
   },
   {
    "uid": "700367142",
    "gacha_type": "301",
    "item_id": "",
    "count": "1",
    "time": "2021-09-05 07:39:24",
    "name": "Emerald Orb",
    "lang": "en-us",
    "item_type": "Weapon",
    "rank_type": "3",
    "id": "1630821960000131389"
   },
   {
    "uid": "700367142",
    "gacha_type": "301",
    "item_id": "",
    "count": "1",
    "time": "2021-09-03 20:05:43",
    "name": "Debate Club",
    "lang": "en-us",
    "item_type": "Weapon",
    "rank_type": "3",
    "id": "1630695960000066028"
   },
   {
    "uid": "700367142",
    "gacha_type": "301",
    "item_id": "",
    "count": "1",
    "time": "2021-09-03 20:05:43",
    "name": "The Widsith",
    "lang": "en-us",
    "item_type": "Weapon",
    "rank_type": "4",
    "id": "1630695960000066027"
   },
   {
    "uid": "700367142",
    "gacha_type": "301",
    "item_id": "",
    "count": "1",
    "time": "2021-09-03 20:05:43",
    "name": "Raven Bow",
    "lang": "en-us",
    "item_type": "Weapon",
    "rank_type": "3",
    "id": "1630695960000066026"
   },
   {
    "uid": "700367142",
    "gacha_type": "301",
    "item_id": "",
    "count": "1",
    "time": "2021-09-03 20:05:43",
    "name": "Harbinger of Dawn",
    "lang": "en-us",
    "item_type": "Weapon",
    "rank_type": "3",
    "id": "1630695960000066025"
   },
   {
    "uid": "700367142",
    "gacha_type": "301",
    "item_id": "",
    "count": "1",
    "time": "2021-09-03 20:05:43",
    "name": "Emerald Orb",
    "lang": "en-us",
    "item_type": "Weapon",
    "rank_type": "3",
    "id": "1630695960000066024"
   },
   {
    "uid": "700367142",
    "gacha_type": "301",
    "item_id": "",
    "count": "1",
    "time": "2021-09-03 20:05:43",
    "name": "Harbinger of Dawn",
    "lang": "en-us",
    "item_type": "Weapon",
    "rank_type": "3",
    "id": "1630695960000066023"
   },
   {
    "uid": "700367142",
    "gacha_type": "301",
    "item_id": "",
    "count": "1",
    "time": "2021-09-03 20:05:43",
    "name": "Ferrous Shadow",
    "lang": "en-us",
    "item_type": "Weapon",
    "rank_type": "3",
    "id": "1630695960000066022"
   },
   {
    "uid": "700367142",
    "gacha_type": "301",
    "item_id": "",
    "count": "1",
    "time": "2021-09-03 20:05:43",
    "name": "Kujou Sara",
    "lang": "en-us",
    "item_type": "Character",
    "rank_type": "4",
    "id": "1630695960000066021"
   },
   {
    "uid": "700367142",
    "gacha_type": "301",
    "item_id": "",
    "count": "1",
    "time": "2021-09-03 20:05:43",
    "name": "Skyrider Sword",
    "lang": "en-us",
    "item_type": "Weapon",
    "rank_type": "3",
    "id": "1630695960000066020"
   },
   {
    "uid": "700367142",
    "gacha_type": "301",
    "item_id": "",
    "count": "1",
    "time": "2021-09-03 20:05:43",
    "name": "Sharpshooter's Oath",
    "lang": "en-us",
    "item_type": "Weapon",
    "rank_type": "3",
    "id": "1630695960000066019"
   },
   {
    "uid": "700367142",
    "gacha_type": "301",
    "item_id": "",
    "count": "1",
    "time": "2021-09-02 15:29:44",
    "name": "Skyrider Sword",
    "lang": "en-us",
    "item_type": "Weapon",
    "rank_type": "3",
    "id": "1630591560000420924"
   },
   {
    "uid": "700367142",
    "gacha_type": "301",
    "item_id": "",
    "count": "1",
    "time": "2021-09-02 15:29:25",
    "name": "Cool Steel",
    "lang": "en-us",
    "item_type": "Weapon",
    "rank_type": "3",
    "id": "1630591560000416228"
   },
   {
    "uid": "700367142",
    "gacha_type": "301",
    "item_id": "",
    "count": "1",
    "time": "2021-09-01 04:34:54",
    "name": "Black Tassel",
    "lang": "en-us",
    "item_type": "Weapon",
    "rank_type": "3",
    "id": "1630465560003317842"
   },
   {
    "uid": "700367142",
    "gacha_type": "301",
    "item_id": "",
    "count": "1",
    "time": "2021-09-01 04:34:54",
    "name": "Cool Steel",
    "lang": "en-us",
    "item_type": "Weapon",
    "rank_type": "3",
    "id": "1630465560003317841"
   },
   {
    "uid": "700367142",
    "gacha_type": "301",
    "item_id": "",
    "count": "1",
    "time": "2021-09-01 04:34:54",
    "name": "Debate Club",
    "lang": "en-us",
    "item_type": "Weapon",
    "rank_type": "3",
    "id": "1630465560003317840"
   },
   {
    "uid": "700367142",
    "gacha_type": "301",
    "item_id": "",
    "count": "1",
    "time": "2021-09-01 04:34:54",
    "name": "Thrilling Tales of Dragon Slayers",
    "lang": "en-us",
    "item_type": "Weapon",
    "rank_type": "3",
    "id": "1630465560003317839"
   },
   {
    "uid": "700367142",
    "gacha_type": "301",
    "item_id": "",
    "count": "1",
    "time": "2021-09-01 04:34:54",
    "name": "Thrilling Tales of Dragon Slayers",
    "lang": "en-us",
    "item_type": "Weapon",
    "rank_type": "3",
    "id": "1630465560003317838"
   },
   {
    "uid": "700367142",
    "gacha_type": "301",
    "item_id": "",
    "count": "1",
    "time": "2021-09-01 04:34:54",
    "name": "Lion's Roar",
    "lang": "en-us",
    "item_type": "Weapon",
    "rank_type": "4",
    "id": "1630465560003317837"
   },
   {
    "uid": "700367142",
    "gacha_type": "301",
    "item_id": "",
    "count": "1",
    "time": "2021-09-01 04:34:54",
    "name": "Skyrider Sword",
    "lang": "en-us",
    "item_type": "Weapon",
    "rank_type": "3",
    "id": "1630465560003317836"
   },
   {
    "uid": "700367142",
    "gacha_type": "301",
    "item_id": "",
    "count": "1",
    "time": "2021-09-01 04:34:54",
    "name": "Black Tassel",
    "lang": "en-us",
    "item_type": "Weapon",
    "rank_type": "3",
    "id": "1630465560003317835"
   },
   {
    "uid": "700367142",
    "gacha_type": "301",
    "item_id": "",
    "count": "1",
    "time": "2021-09-01 04:34:54",
    "name": "Magic Guide",
    "lang": "en-us",
    "item_type": "Weapon",
    "rank_type": "3",
    "id": "1630465560003317834"
   },
   {
    "uid": "700367142",
    "gacha_type": "301",
    "item_id": "",
    "count": "1",
    "time": "2021-09-01 04:34:54",
    "name": "Magic Guide",
    "lang": "en-us",
    "item_type": "Weapon",
    "rank_type": "3",
    "id": "1630465560003317833"
   },
   {
    "uid": "700367142",
    "gacha_type": "301",
    "item_id": "",
    "count": "1",
    "time": "2021-08-20 19:22:54",
    "name": "Sayu",
    "lang": "en-us",
    "item_type": "Character",
    "rank_type": "4",
    "id": "1629482760000165685"
   },
   {
    "uid": "700367142",
    "gacha_type": "301",
    "item_id": "",
    "count": "1",
    "time": "2021-08-19 19:55:04",
    "name": "Slingshot",
    "lang": "en-us",
    "item_type": "Weapon",
    "rank_type": "3",
    "id": "1629396360000246700"
   },
   {
    "uid": "700367142",
    "gacha_type": "301",
    "item_id": "",
    "count": "1",
    "time": "2021-08-19 19:55:00",
    "name": "Raven Bow",
    "lang": "en-us",
    "item_type": "Weapon",
    "rank_type": "3",
    "id": "1629396360000246386"
   },
   {
    "uid": "700367142",
    "gacha_type": "301",
    "item_id": "",
    "count": "1",
    "time": "2021-08-19 19:54:51",
    "name": "Ferrous Shadow",
    "lang": "en-us",
    "item_type": "Weapon",
    "rank_type": "3",
    "id": "1629396360000245755"
   },
   {
    "uid": "700367142",
    "gacha_type": "301",
    "item_id": "",
    "count": "1",
    "time": "2021-08-12 18:59:06",
    "name": "Magic Guide",
    "lang": "en-us",
    "item_type": "Weapon",
    "rank_type": "3",
    "id": "1628787960000371058"
   },
   {
    "uid": "700367142",
    "gacha_type": "301",
    "item_id": "",
    "count": "1",
    "time": "2021-08-12 18:58:58",
    "name": "Slingshot",
    "lang": "en-us",
    "item_type": "Weapon",
    "rank_type": "3",
    "id": "1628787960000370255"
   },
   {
    "uid": "700367142",
    "gacha_type": "301",
    "item_id": "",
    "count": "1",
    "time": "2021-08-09 19:42:37",
    "name": "Chongyun",
    "lang": "en-us",
    "item_type": "Character",
    "rank_type": "4",
    "id": "1628532360000223149"
   },
   {
    "uid": "700367142",
    "gacha_type": "301",
    "item_id": "",
    "count": "1",
    "time": "2021-08-09 19:39:30",
    "name": "Debate Club",
    "lang": "en-us",
    "item_type": "Weapon",
    "rank_type": "3",
    "id": "1628532360000206429"
   },
   {
    "uid": "700367142",
    "gacha_type": "301",
    "item_id": "",
    "count": "1",
    "time": "2021-08-09 19:39:21",
    "name": "Black Tassel",
    "lang": "en-us",
    "item_type": "Weapon",
    "rank_type": "3",
    "id": "1628532360000205709"
   },
   {
    "uid": "700367142",
    "gacha_type": "301",
    "item_id": "",
    "count": "1",
    "time": "2021-08-06 08:35:28",
    "name": "Debate Club",
    "lang": "en-us",
    "item_type": "Weapon",
    "rank_type": "3",
    "id": "1628233560000102788"
   },
   {
    "uid": "700367142",
    "gacha_type": "301",
    "item_id": "",
    "count": "1",
    "time": "2021-08-04 10:09:45",
    "name": "Bloodtainted Greatsword",
    "lang": "en-us",
    "item_type": "Weapon",
    "rank_type": "3",
    "id": "1628067960000050026"
   },
   {
    "uid": "700367142",
    "gacha_type": "301",
    "item_id": "",
    "count": "1",
    "time": "2021-08-01 16:51:25",
    "name": "Emerald Orb",
    "lang": "en-us",
    "item_type": "Weapon",
    "rank_type": "3",
    "id": "1627830360000543336"
   },
   {
    "uid": "700367142",
    "gacha_type": "301",
    "item_id": "",
    "count": "1",
    "time": "2021-08-01 16:51:18",
    "name": "Thrilling Tales of Dragon Slayers",
    "lang": "en-us",
    "item_type": "Weapon",
    "rank_type": "3",
    "id": "1627830360000542130"
   },
   {
    "uid": "700367142",
    "gacha_type": "301",
    "item_id": "",
    "count": "1",
    "time": "2021-08-01 16:51:11",
    "name": "Debate Club",
    "lang": "en-us",
    "item_type": "Weapon",
    "rank_type": "3",
    "id": "1627830360000541040"
   },
   {
    "uid": "700367142",
    "gacha_type": "301",
    "item_id": "",
    "count": "1",
    "time": "2021-08-01 16:51:02",
    "name": "Yanfei",
    "lang": "en-us",
    "item_type": "Character",
    "rank_type": "4",
    "id": "1627830360000539451"
   },
   {
    "uid": "700367142",
    "gacha_type": "301",
    "item_id": "",
    "count": "1",
    "time": "2021-08-01 16:50:56",
    "name": "Raven Bow",
    "lang": "en-us",
    "item_type": "Weapon",
    "rank_type": "3",
    "id": "1627830360000538455"
   },
   {
    "uid": "700367142",
    "gacha_type": "301",
    "item_id": "",
    "count": "1",
    "time": "2021-08-01 16:50:50",
    "name": "Black Tassel",
    "lang": "en-us",
    "item_type": "Weapon",
    "rank_type": "3",
    "id": "1627830360000537477"
   },
   {
    "uid": "700367142",
    "gacha_type": "301",
    "item_id": "",
    "count": "1",
    "time": "2021-08-01 16:50:44",
    "name": "Sharpshooter's Oath",
    "lang": "en-us",
    "item_type": "Weapon",
    "rank_type": "3",
    "id": "1627830360000536451"
   },
   {
    "uid": "700367142",
    "gacha_type": "301",
    "item_id": "",
    "count": "1",
    "time": "2021-07-30 19:49:46",
    "name": "Emerald Orb",
    "lang": "en-us",
    "item_type": "Weapon",
    "rank_type": "3",
    "id": "1627668360000276842"
   },
   {
    "uid": "700367142",
    "gacha_type": "301",
    "item_id": "",
    "count": "1",
    "time": "2021-07-30 19:49:37",
    "name": "Magic Guide",
    "lang": "en-us",
    "item_type": "Weapon",
    "rank_type": "3",
    "id": "1627668360000276036"
   },
   {
    "uid": "700367142",
    "gacha_type": "301",
    "item_id": "",
    "count": "1",
    "time": "2021-07-26 14:39:34",
    "name": "Magic Guide",
    "lang": "en-us",
    "item_type": "Weapon",
    "rank_type": "3",
    "id": "1627304760000251804"
   },
   {
    "uid": "700367142",
    "gacha_type": "301",
    "item_id": "",
    "count": "1",
    "time": "2021-07-26 14:39:26",
    "name": "Raven Bow",
    "lang": "en-us",
    "item_type": "Weapon",
    "rank_type": "3",
    "id": "1627304760000250938"
   },
   {
    "uid": "700367142",
    "gacha_type": "301",
    "item_id": "",
    "count": "1",
    "time": "2021-07-26 14:39:20",
    "name": "Cool Steel",
    "lang": "en-us",
    "item_type": "Weapon",
    "rank_type": "3",
    "id": "1627304760000250368"
   },
   {
    "uid": "700367142",
    "gacha_type": "301",
    "item_id": "",
    "count": "1",
    "time": "2021-07-26 14:39:14",
    "name": "Magic Guide",
    "lang": "en-us",
    "item_type": "Weapon",
    "rank_type": "3",
    "id": "1627304760000249801"
   },
   {
    "uid": "700367142",
    "gacha_type": "301",
    "item_id": "",
    "count": "1",
    "time": "2021-07-26 14:39:04",
    "name": "The Stringless",
    "lang": "en-us",
    "item_type": "Weapon",
    "rank_type": "4",
    "id": "1627304760000248702"
   },
   {
    "uid": "700367142",
    "gacha_type": "301",
    "item_id": "",
    "count": "1",
    "time": "2021-07-26 14:38:55",
    "name": "Slingshot",
    "lang": "en-us",
    "item_type": "Weapon",
    "rank_type": "3",
    "id": "1627304760000247808"
   },
   {
    "uid": "700367142",
    "gacha_type": "301",
    "item_id": "",
    "count": "1",
    "time": "2021-07-23 13:25:47",
    "name": "Slingshot",
    "lang": "en-us",
    "item_type": "Weapon",
    "rank_type": "3",
    "id": "1627041960000202450"
   },
   {
    "uid": "700367142",
    "gacha_type": "301",
    "item_id": "",
    "count": "1",
    "time": "2021-07-23 13:25:41",
    "name": "Skyrider Sword",
    "lang": "en-us",
    "item_type": "Weapon",
    "rank_type": "3",
    "id": "1627041960000201609"
   },
   {
    "uid": "700367142",
    "gacha_type": "301",
    "item_id": "",
    "count": "1",
    "time": "2021-07-21 05:10:45",
    "name": "Sharpshooter's Oath",
    "lang": "en-us",
    "item_type": "Weapon",
    "rank_type": "3",
    "id": "1626840360000218408"
   },
   {
    "uid": "700367142",
    "gacha_type": "301",
    "item_id": "",
    "count": "1",
    "time": "2021-07-21 05:10:45",
    "name": "Debate Club",
    "lang": "en-us",
    "item_type": "Weapon",
    "rank_type": "3",
    "id": "1626840360000218407"
   },
   {
    "uid": "700367142",
    "gacha_type": "301",
    "item_id": "",
    "count": "1",
    "time": "2021-07-21 05:10:45",
    "name": "Skyrider Sword",
    "lang": "en-us",
    "item_type": "Weapon",
    "rank_type": "3",
    "id": "1626840360000218406"
   },
   {
    "uid": "700367142",
    "gacha_type": "301",
    "item_id": "",
    "count": "1",
    "time": "2021-07-21 05:10:45",
    "name": "Thrilling Tales of Dragon Slayers",
    "lang": "en-us",
    "item_type": "Weapon",
    "rank_type": "3",
    "id": "1626840360000218405"
   },
   {
    "uid": "700367142",
    "gacha_type": "301",
    "item_id": "",
    "count": "1",
    "time": "2021-07-21 05:10:45",
    "name": "Slingshot",
    "lang": "en-us",
    "item_type": "Weapon",
    "rank_type": "3",
    "id": "1626840360000218404"
   },
   {
    "uid": "700367142",
    "gacha_type": "301",
    "item_id": "",
    "count": "1",
    "time": "2021-07-21 05:10:45",
    "name": "Magic Guide",
    "lang": "en-us",
    "item_type": "Weapon",
    "rank_type": "3",
    "id": "1626840360000218403"
   },
   {
    "uid": "700367142",
    "gacha_type": "301",
    "item_id": "",
    "count": "1",
    "time": "2021-07-21 05:10:45",
    "name": "Ningguang",
    "lang": "en-us",
    "item_type": "Character",
    "rank_type": "4",
    "id": "1626840360000218402"
   },
   {
    "uid": "700367142",
    "gacha_type": "301",
    "item_id": "",
    "count": "1",
    "time": "2021-07-21 05:10:45",
    "name": "Slingshot",
    "lang": "en-us",
    "item_type": "Weapon",
    "rank_type": "3",
    "id": "1626840360000218401"
   },
   {
    "uid": "700367142",
    "gacha_type": "301",
    "item_id": "",
    "count": "1",
    "time": "2021-07-21 05:10:45",
    "name": "Thrilling Tales of Dragon Slayers",
    "lang": "en-us",
    "item_type": "Weapon",
    "rank_type": "3",
    "id": "1626840360000218400"
   },
   {
    "uid": "700367142",
    "gacha_type": "301",
    "item_id": "",
    "count": "1",
    "time": "2021-07-21 05:10:45",
    "name": "Raven Bow",
    "lang": "en-us",
    "item_type": "Weapon",
    "rank_type": "3",
    "id": "1626840360000218399"
   },
   {
    "uid": "700367142",
    "gacha_type": "301",
    "item_id": "",
    "count": "1",
    "time": "2021-07-21 05:07:13",
    "name": "Raven Bow",
    "lang": "en-us",
    "item_type": "Weapon",
    "rank_type": "3",
    "id": "1626840360000147268"
   },
   {
    "uid": "700367142",
    "gacha_type": "301",
    "item_id": "",
    "count": "1",
    "time": "2021-07-21 05:07:13",
    "name": "Cool Steel",
    "lang": "en-us",
    "item_type": "Weapon",
    "rank_type": "3",
    "id": "1626840360000147267"
   },
   {
    "uid": "700367142",
    "gacha_type": "301",
    "item_id": "",
    "count": "1",
    "time": "2021-07-21 05:07:13",
    "name": "Debate Club",
    "lang": "en-us",
    "item_type": "Weapon",
    "rank_type": "3",
    "id": "1626840360000147266"
   },
   {
    "uid": "700367142",
    "gacha_type": "301",
    "item_id": "",
    "count": "1",
    "time": "2021-07-21 05:07:13",
    "name": "Slingshot",
    "lang": "en-us",
    "item_type": "Weapon",
    "rank_type": "3",
    "id": "1626840360000147265"
   },
   {
    "uid": "700367142",
    "gacha_type": "301",
    "item_id": "",
    "count": "1",
    "time": "2021-07-21 05:07:13",
    "name": "Ferrous Shadow",
    "lang": "en-us",
    "item_type": "Weapon",
    "rank_type": "3",
    "id": "1626840360000147264"
   },
   {
    "uid": "700367142",
    "gacha_type": "301",
    "item_id": "",
    "count": "1",
    "time": "2021-07-21 05:07:13",
    "name": "Kamisato Ayaka",
    "lang": "en-us",
    "item_type": "Character",
    "rank_type": "5",
    "id": "1626840360000147263"
   },
   {
    "uid": "700367142",
    "gacha_type": "301",
    "item_id": "",
    "count": "1",
    "time": "2021-07-21 05:07:13",
    "name": "Sacrificial Greatsword",
    "lang": "en-us",
    "item_type": "Weapon",
    "rank_type": "4",
    "id": "1626840360000147262"
   },
   {
    "uid": "700367142",
    "gacha_type": "301",
    "item_id": "",
    "count": "1",
    "time": "2021-07-21 05:07:13",
    "name": "Ferrous Shadow",
    "lang": "en-us",
    "item_type": "Weapon",
    "rank_type": "3",
    "id": "1626840360000147261"
   },
   {
    "uid": "700367142",
    "gacha_type": "301",
    "item_id": "",
    "count": "1",
    "time": "2021-07-21 05:07:13",
    "name": "Magic Guide",
    "lang": "en-us",
    "item_type": "Weapon",
    "rank_type": "3",
    "id": "1626840360000147260"
   },
   {
    "uid": "700367142",
    "gacha_type": "301",
    "item_id": "",
    "count": "1",
    "time": "2021-07-21 05:07:13",
    "name": "Skyrider Sword",
    "lang": "en-us",
    "item_type": "Weapon",
    "rank_type": "3",
    "id": "1626840360000147259"
   },
   {
    "uid": "700367142",
    "gacha_type": "301",
    "item_id": "",
    "count": "1",
    "time": "2021-07-21 05:03:29",
    "name": "Ferrous Shadow",
    "lang": "en-us",
    "item_type": "Weapon",
    "rank_type": "3",
    "id": "1626840360000070649"
   },
   {
    "uid": "700367142",
    "gacha_type": "301",
    "item_id": "",
    "count": "1",
    "time": "2021-07-21 05:03:29",
    "name": "Debate Club",
    "lang": "en-us",
    "item_type": "Weapon",
    "rank_type": "3",
    "id": "1626840360000070648"
   },
   {
    "uid": "700367142",
    "gacha_type": "301",
    "item_id": "",
    "count": "1",
    "time": "2021-07-21 05:03:29",
    "name": "Emerald Orb",
    "lang": "en-us",
    "item_type": "Weapon",
    "rank_type": "3",
    "id": "1626840360000070647"
   },
   {
    "uid": "700367142",
    "gacha_type": "301",
    "item_id": "",
    "count": "1",
    "time": "2021-07-21 05:03:29",
    "name": "Thrilling Tales of Dragon Slayers",
    "lang": "en-us",
    "item_type": "Weapon",
    "rank_type": "3",
    "id": "1626840360000070646"
   },
   {
    "uid": "700367142",
    "gacha_type": "301",
    "item_id": "",
    "count": "1",
    "time": "2021-07-21 05:03:29",
    "name": "Cool Steel",
    "lang": "en-us",
    "item_type": "Weapon",
    "rank_type": "3",
    "id": "1626840360000070645"
   },
   {
    "uid": "700367142",
    "gacha_type": "301",
    "item_id": "",
    "count": "1",
    "time": "2021-07-21 05:03:29",
    "name": "Ningguang",
    "lang": "en-us",
    "item_type": "Character",
    "rank_type": "4",
    "id": "1626840360000070644"
   },
   {
    "uid": "700367142",
    "gacha_type": "301",
    "item_id": "",
    "count": "1",
    "time": "2021-07-21 05:03:29",
    "name": "Raven Bow",
    "lang": "en-us",
    "item_type": "Weapon",
    "rank_type": "3",
    "id": "1626840360000070643"
   },
   {
    "uid": "700367142",
    "gacha_type": "301",
    "item_id": "",
    "count": "1",
    "time": "2021-07-21 05:03:29",
    "name": "Black Tassel",
    "lang": "en-us",
    "item_type": "Weapon",
    "rank_type": "3",
    "id": "1626840360000070642"
   },
   {
    "uid": "700367142",
    "gacha_type": "301",
    "item_id": "",
    "count": "1",
    "time": "2021-07-21 05:03:29",
    "name": "Slingshot",
    "lang": "en-us",
    "item_type": "Weapon",
    "rank_type": "3",
    "id": "1626840360000070641"
   },
   {
    "uid": "700367142",
    "gacha_type": "301",
    "item_id": "",
    "count": "1",
    "time": "2021-07-21 05:03:29",
    "name": "Bloodtainted Greatsword",
    "lang": "en-us",
    "item_type": "Weapon",
    "rank_type": "3",
    "id": "1626840360000070640"
   },
   {
    "uid": "700367142",
    "gacha_type": "301",
    "item_id": "",
    "count": "1",
    "time": "2021-05-24 22:48:59",
    "name": "Harbinger of Dawn",
    "lang": "en-us",
    "item_type": "Weapon",
    "rank_type": "3",
    "id": "1621890360000134586"
   },
   {
    "uid": "700367142",
    "gacha_type": "301",
    "item_id": "",
    "count": "1",
    "time": "2021-05-24 13:17:59",
    "name": "Ferrous Shadow",
    "lang": "en-us",
    "item_type": "Weapon",
    "rank_type": "3",
    "id": "1621857960000068906"
   },
   {
    "uid": "700367142",
    "gacha_type": "301",
    "item_id": "",
    "count": "1",
    "time": "2021-05-24 13:17:59",
    "name": "Debate Club",
    "lang": "en-us",
    "item_type": "Weapon",
    "rank_type": "3",
    "id": "1621857960000068905"
   },
   {
    "uid": "700367142",
    "gacha_type": "301",
    "item_id": "",
    "count": "1",
    "time": "2021-05-24 13:17:59",
    "name": "Black Tassel",
    "lang": "en-us",
    "item_type": "Weapon",
    "rank_type": "3",
    "id": "1621857960000068904"
   },
   {
    "uid": "700367142",
    "gacha_type": "301",
    "item_id": "",
    "count": "1",
    "time": "2021-05-24 13:17:59",
    "name": "Harbinger of Dawn",
    "lang": "en-us",
    "item_type": "Weapon",
    "rank_type": "3",
    "id": "1621857960000068903"
   },
   {
    "uid": "700367142",
    "gacha_type": "301",
    "item_id": "",
    "count": "1",
    "time": "2021-05-24 13:17:59",
    "name": "Xinyan",
    "lang": "en-us",
    "item_type": "Character",
    "rank_type": "4",
    "id": "1621857960000068902"
   },
   {
    "uid": "700367142",
    "gacha_type": "301",
    "item_id": "",
    "count": "1",
    "time": "2021-05-24 13:17:59",
    "name": "Skyrider Sword",
    "lang": "en-us",
    "item_type": "Weapon",
    "rank_type": "3",
    "id": "1621857960000068901"
   },
   {
    "uid": "700367142",
    "gacha_type": "301",
    "item_id": "",
    "count": "1",
    "time": "2021-05-24 13:17:59",
    "name": "Thrilling Tales of Dragon Slayers",
    "lang": "en-us",
    "item_type": "Weapon",
    "rank_type": "3",
    "id": "1621857960000068900"
   },
   {
    "uid": "700367142",
    "gacha_type": "301",
    "item_id": "",
    "count": "1",
    "time": "2021-05-24 13:17:59",
    "name": "Ferrous Shadow",
    "lang": "en-us",
    "item_type": "Weapon",
    "rank_type": "3",
    "id": "1621857960000068899"
   },
   {
    "uid": "700367142",
    "gacha_type": "301",
    "item_id": "",
    "count": "1",
    "time": "2021-05-24 13:17:59",
    "name": "Bloodtainted Greatsword",
    "lang": "en-us",
    "item_type": "Weapon",
    "rank_type": "3",
    "id": "1621857960000068898"
   },
   {
    "uid": "700367142",
    "gacha_type": "301",
    "item_id": "",
    "count": "1",
    "time": "2021-05-24 13:17:59",
    "name": "Emerald Orb",
    "lang": "en-us",
    "item_type": "Weapon",
    "rank_type": "3",
    "id": "1621857960000068897"
   }
  ]
 },
 "302": {
  "total": 140,
  "list": [
   {
    "uid": "700367142",
    "gacha_type": "302",
    "item_id": "",
    "count": "1",
    "time": "2021-11-14 10:21:15",
    "name": "Elegy for the End",
    "lang": "en-us",
    "item_type": "Weapon",
    "rank_type": "5",
    "id": "1636880760000078813"
   },
   {
    "uid": "700367142",
    "gacha_type": "302",
    "item_id": "",
    "count": "1",
    "time": "2021-11-12 14:26:43",
    "name": "Harbinger of Dawn",
    "lang": "en-us",
    "item_type": "Weapon",
    "rank_type": "3",
    "id": "1636722360000318532"
   },
   {
    "uid": "700367142",
    "gacha_type": "302",
    "item_id": "",
    "count": "1",
    "time": "2021-11-12 14:26:43",
    "name": "Skyrider Sword",
    "lang": "en-us",
    "item_type": "Weapon",
    "rank_type": "3",
    "id": "1636722360000318531"
   },
   {
    "uid": "700367142",
    "gacha_type": "302",
    "item_id": "",
    "count": "1",
    "time": "2021-11-12 14:26:43",
    "name": "Sharpshooter's Oath",
    "lang": "en-us",
    "item_type": "Weapon",
    "rank_type": "3",
    "id": "1636722360000318530"
   },
   {
    "uid": "700367142",
    "gacha_type": "302",
    "item_id": "",
    "count": "1",
    "time": "2021-11-12 14:26:43",
    "name": "Rainslasher",
    "lang": "en-us",
    "item_type": "Weapon",
    "rank_type": "4",
    "id": "1636722360000318529"
   },
   {
    "uid": "700367142",
    "gacha_type": "302",
    "item_id": "",
    "count": "1",
    "time": "2021-11-12 14:26:43",
    "name": "Emerald Orb",
    "lang": "en-us",
    "item_type": "Weapon",
    "rank_type": "3",
    "id": "1636722360000318528"
   },
   {
    "uid": "700367142",
    "gacha_type": "302",
    "item_id": "",
    "count": "1",
    "time": "2021-11-12 14:26:43",
    "name": "Debate Club",
    "lang": "en-us",
    "item_type": "Weapon",
    "rank_type": "3",
    "id": "1636722360000318527"
   },
   {
    "uid": "700367142",
    "gacha_type": "302",
    "item_id": "",
    "count": "1",
    "time": "2021-11-12 14:26:43",
    "name": "Cool Steel",
    "lang": "en-us",
    "item_type": "Weapon",
    "rank_type": "3",
    "id": "1636722360000318526"
   },
   {
    "uid": "700367142",
    "gacha_type": "302",
    "item_id": "",
    "count": "1",
    "time": "2021-11-12 14:26:43",
    "name": "Ferrous Shadow",
    "lang": "en-us",
    "item_type": "Weapon",
    "rank_type": "3",
    "id": "1636722360000318525"
   },
   {
    "uid": "700367142",
    "gacha_type": "302",
    "item_id": "",
    "count": "1",
    "time": "2021-11-12 14:26:43",
    "name": "Harbinger of Dawn",
    "lang": "en-us",
    "item_type": "Weapon",
    "rank_type": "3",
    "id": "1636722360000318524"
   },
   {
    "uid": "700367142",
    "gacha_type": "302",
    "item_id": "",
    "count": "1",
    "time": "2021-11-12 14:26:43",
    "name": "Emerald Orb",
    "lang": "en-us",
    "item_type": "Weapon",
    "rank_type": "3",
    "id": "1636722360000318523"
   },
   {
    "uid": "700367142",
    "gacha_type": "302",
    "item_id": "",
    "count": "1",
    "time": "2021-11-02 18:06:27",
    "name": "Ferrous Shadow",
    "lang": "en-us",
    "item_type": "Weapon",
    "rank_type": "3",
    "id": "1635872760012139450"
   },
   {
    "uid": "700367142",
    "gacha_type": "302",
    "item_id": "",
    "count": "1",
    "time": "2021-11-02 18:06:17",
    "name": "Bennett",
    "lang": "en-us",
    "item_type": "Character",
    "rank_type": "4",
    "id": "1635872760011870937"
   },
   {
    "uid": "700367142",
    "gacha_type": "302",
    "item_id": "",
    "count": "1",
    "time": "2021-11-02 18:06:11",
    "name": "Cool Steel",
    "lang": "en-us",
    "item_type": "Weapon",
    "rank_type": "3",
    "id": "1635872760011707795"
   },
   {
    "uid": "700367142",
    "gacha_type": "302",
    "item_id": "",
    "count": "1",
    "time": "2021-11-02 18:06:05",
    "name": "Black Tassel",
    "lang": "en-us",
    "item_type": "Weapon",
    "rank_type": "3",
    "id": "1635872760011545196"
   },
   {
    "uid": "700367142",
    "gacha_type": "302",
    "item_id": "",
    "count": "1",
    "time": "2021-11-02 18:05:33",
    "name": "Cool Steel",
    "lang": "en-us",
    "item_type": "Weapon",
    "rank_type": "3",
    "id": "1635872760010639868"
   },
   {
    "uid": "700367142",
    "gacha_type": "302",
    "item_id": "",
    "count": "1",
    "time": "2021-11-02 18:05:33",
    "name": "Magic Guide",
    "lang": "en-us",
    "item_type": "Weapon",
    "rank_type": "3",
    "id": "1635872760010639867"
   },
   {
    "uid": "700367142",
    "gacha_type": "302",
    "item_id": "",
    "count": "1",
    "time": "2021-11-02 18:05:33",
    "name": "Magic Guide",
    "lang": "en-us",
    "item_type": "Weapon",
    "rank_type": "3",
    "id": "1635872760010639866"
   },
   {
    "uid": "700367142",
    "gacha_type": "302",
    "item_id": "",
    "count": "1",
    "time": "2021-11-02 18:05:33",
    "name": "Thrilling Tales of Dragon Slayers",
    "lang": "en-us",
    "item_type": "Weapon",
    "rank_type": "3",
    "id": "1635872760010639865"
   },
   {
    "uid": "700367142",
    "gacha_type": "302",
    "item_id": "",
    "count": "1",
    "time": "2021-11-02 18:05:33",
    "name": "Debate Club",
    "lang": "en-us",
    "item_type": "Weapon",
    "rank_type": "3",
    "id": "1635872760010639864"
   },
   {
    "uid": "700367142",
    "gacha_type": "302",
    "item_id": "",
    "count": "1",
    "time": "2021-11-02 18:05:33",
    "name": "Mouun's Moon",
    "lang": "en-us",
    "item_type": "Weapon",
    "rank_type": "4",
    "id": "1635872760010639863"
   },
   {
    "uid": "700367142",
    "gacha_type": "302",
    "item_id": "",
    "count": "1",
    "time": "2021-11-02 18:05:33",
    "name": "Magic Guide",
    "lang": "en-us",
    "item_type": "Weapon",
    "rank_type": "3",
    "id": "1635872760010639862"
   },
   {
    "uid": "700367142",
    "gacha_type": "302",
    "item_id": "",
    "count": "1",
    "time": "2021-11-02 18:05:33",
    "name": "Harbinger of Dawn",
    "lang": "en-us",
    "item_type": "Weapon",
    "rank_type": "3",
    "id": "1635872760010639861"
   },
   {
    "uid": "700367142",
    "gacha_type": "302",
    "item_id": "",
    "count": "1",
    "time": "2021-11-02 18:05:33",
    "name": "Sharpshooter's Oath",
    "lang": "en-us",
    "item_type": "Weapon",
    "rank_type": "3",
    "id": "1635872760010639860"
   },
   {
    "uid": "700367142",
    "gacha_type": "302",
    "item_id": "",
    "count": "1",
    "time": "2021-11-02 18:05:33",
    "name": "Slingshot",
    "lang": "en-us",
    "item_type": "Weapon",
    "rank_type": "3",
    "id": "1635872760010639859"
   },
   {
    "uid": "700367142",
    "gacha_type": "302",
    "item_id": "",
    "count": "1",
    "time": "2021-11-02 18:05:21",
    "name": "Magic Guide",
    "lang": "en-us",
    "item_type": "Weapon",
    "rank_type": "3",
    "id": "1635872760010289212"
   },
   {
    "uid": "700367142",
    "gacha_type": "302",
    "item_id": "",
    "count": "1",
    "time": "2021-11-02 18:05:21",
    "name": "Harbinger of Dawn",
    "lang": "en-us",
    "item_type": "Weapon",
    "rank_type": "3",
    "id": "1635872760010289211"
   },
   {
    "uid": "700367142",
    "gacha_type": "302",
    "item_id": "",
    "count": "1",
    "time": "2021-11-02 18:05:21",
    "name": "Sharpshooter's Oath",
    "lang": "en-us",
    "item_type": "Weapon",
    "rank_type": "3",
    "id": "1635872760010289210"
   },
   {
    "uid": "700367142",
    "gacha_type": "302",
    "item_id": "",
    "count": "1",
    "time": "2021-11-02 18:05:21",
    "name": "Black Tassel",
    "lang": "en-us",
    "item_type": "Weapon",
    "rank_type": "3",
    "id": "1635872760010289209"
   },
   {
    "uid": "700367142",
    "gacha_type": "302",
    "item_id": "",
    "count": "1",
    "time": "2021-11-02 18:05:21",
    "name": "Mouun's Moon",
    "lang": "en-us",
    "item_type": "Weapon",
    "rank_type": "4",
    "id": "1635872760010289208"
   },
   {
    "uid": "700367142",
    "gacha_type": "302",
    "item_id": "",
    "count": "1",
    "time": "2021-11-02 18:05:21",
    "name": "Cool Steel",
    "lang": "en-us",
    "item_type": "Weapon",
    "rank_type": "3",
    "id": "1635872760010289207"
   },
   {
    "uid": "700367142",
    "gacha_type": "302",
    "item_id": "",
    "count": "1",
    "time": "2021-11-02 18:05:21",
    "name": "Cool Steel",
    "lang": "en-us",
    "item_type": "Weapon",
    "rank_type": "3",
    "id": "1635872760010289206"
   },
   {
    "uid": "700367142",
    "gacha_type": "302",
    "item_id": "",
    "count": "1",
    "time": "2021-11-02 18:05:21",
    "name": "Harbinger of Dawn",
    "lang": "en-us",
    "item_type": "Weapon",
    "rank_type": "3",
    "id": "1635872760010289205"
   },
   {
    "uid": "700367142",
    "gacha_type": "302",
    "item_id": "",
    "count": "1",
    "time": "2021-11-02 18:05:21",
    "name": "Raven Bow",
    "lang": "en-us",
    "item_type": "Weapon",
    "rank_type": "3",
    "id": "1635872760010289204"
   },
   {
    "uid": "700367142",
    "gacha_type": "302",
    "item_id": "",
    "count": "1",
    "time": "2021-11-02 18:05:21",
    "name": "Magic Guide",
    "lang": "en-us",
    "item_type": "Weapon",
    "rank_type": "3",
    "id": "1635872760010289203"
   },
   {
    "uid": "700367142",
    "gacha_type": "302",
    "item_id": "",
    "count": "1",
    "time": "2021-11-02 18:05:01",
    "name": "Wavebreaker's Fin",
    "lang": "en-us",
    "item_type": "Weapon",
    "rank_type": "4",
    "id": "1635872760009689732"
   },
   {
    "uid": "700367142",
    "gacha_type": "302",
    "item_id": "",
    "count": "1",
    "time": "2021-11-02 18:05:01",
    "name": "Ferrous Shadow",
    "lang": "en-us",
    "item_type": "Weapon",
    "rank_type": "3",
    "id": "1635872760009689731"
   },
   {
    "uid": "700367142",
    "gacha_type": "302",
    "item_id": "",
    "count": "1",
    "time": "2021-11-02 18:05:01",
    "name": "Raven Bow",
    "lang": "en-us",
    "item_type": "Weapon",
    "rank_type": "3",
    "id": "1635872760009689730"
   },
   {
    "uid": "700367142",
    "gacha_type": "302",
    "item_id": "",
    "count": "1",
    "time": "2021-11-02 18:05:01",
    "name": "Debate Club",
    "lang": "en-us",
    "item_type": "Weapon",
    "rank_type": "3",
    "id": "1635872760009689729"
   },
   {
    "uid": "700367142",
    "gacha_type": "302",
    "item_id": "",
    "count": "1",
    "time": "2021-11-02 18:05:01",
    "name": "Raven Bow",
    "lang": "en-us",
    "item_type": "Weapon",
    "rank_type": "3",
    "id": "1635872760009689728"
   },
   {
    "uid": "700367142",
    "gacha_type": "302",
    "item_id": "",
    "count": "1",
    "time": "2021-11-02 18:05:01",
    "name": "Magic Guide",
    "lang": "en-us",
    "item_type": "Weapon",
    "rank_type": "3",
    "id": "1635872760009689727"
   },
   {
    "uid": "700367142",
    "gacha_type": "302",
    "item_id": "",
    "count": "1",
    "time": "2021-11-02 18:05:01",
    "name": "Skyrider Sword",
    "lang": "en-us",
    "item_type": "Weapon",
    "rank_type": "3",
    "id": "1635872760009689726"
   },
   {
    "uid": "700367142",
    "gacha_type": "302",
    "item_id": "",
    "count": "1",
    "time": "2021-11-02 18:05:01",
    "name": "Sharpshooter's Oath",
    "lang": "en-us",
    "item_type": "Weapon",
    "rank_type": "3",
    "id": "1635872760009689725"
   },
   {
    "uid": "700367142",
    "gacha_type": "302",
    "item_id": "",
    "count": "1",
    "time": "2021-11-02 18:05:01",
    "name": "Slingshot",
    "lang": "en-us",
    "item_type": "Weapon",
    "rank_type": "3",
    "id": "1635872760009689724"
   },
   {
    "uid": "700367142",
    "gacha_type": "302",
    "item_id": "",
    "count": "1",
    "time": "2021-11-02 18:05:01",
    "name": "Wavebreaker's Fin",
    "lang": "en-us",
    "item_type": "Weapon",
    "rank_type": "4",
    "id": "1635872760009689723"
   },
   {
    "uid": "700367142",
    "gacha_type": "302",
    "item_id": "",
    "count": "1",
    "time": "2021-11-02 18:04:14",
    "name": "Debate Club",
    "lang": "en-us",
    "item_type": "Weapon",
    "rank_type": "3",
    "id": "1635872760008201323"
   },
   {
    "uid": "700367142",
    "gacha_type": "302",
    "item_id": "",
    "count": "1",
    "time": "2021-11-02 18:04:14",
    "name": "Harbinger of Dawn",
    "lang": "en-us",
    "item_type": "Weapon",
    "rank_type": "3",
    "id": "1635872760008201322"
   },
   {
    "uid": "700367142",
    "gacha_type": "302",
    "item_id": "",
    "count": "1",
    "time": "2021-11-02 18:04:14",
    "name": "Harbinger of Dawn",
    "lang": "en-us",
    "item_type": "Weapon",
    "rank_type": "3",
    "id": "1635872760008201321"
   },
   {
    "uid": "700367142",
    "gacha_type": "302",
    "item_id": "",
    "count": "1",
    "time": "2021-11-02 18:04:14",
    "name": "Cool Steel",
    "lang": "en-us",
    "item_type": "Weapon",
    "rank_type": "3",
    "id": "1635872760008201320"
   },
   {
    "uid": "700367142",
    "gacha_type": "302",
    "item_id": "",
    "count": "1",
    "time": "2021-11-02 18:04:14",
    "name": "Debate Club",
    "lang": "en-us",
    "item_type": "Weapon",
    "rank_type": "3",
    "id": "1635872760008201319"
   },
   {
    "uid": "700367142",
    "gacha_type": "302",
    "item_id": "",
    "count": "1",
    "time": "2021-11-02 18:04:14",
    "name": "Black Tassel",
    "lang": "en-us",
    "item_type": "Weapon",
    "rank_type": "3",
    "id": "1635872760008201318"
   },
   {
    "uid": "700367142",
    "gacha_type": "302",
    "item_id": "",
    "count": "1",
    "time": "2021-11-02 18:04:14",
    "name": "Black Tassel",
    "lang": "en-us",
    "item_type": "Weapon",
    "rank_type": "3",
    "id": "1635872760008201317"
   },
   {
    "uid": "700367142",
    "gacha_type": "302",
    "item_id": "",
    "count": "1",
    "time": "2021-11-02 18:04:14",
    "name": "Sacrificial Sword",
    "lang": "en-us",
    "item_type": "Weapon",
    "rank_type": "4",
    "id": "1635872760008201316"
   },
   {
    "uid": "700367142",
    "gacha_type": "302",
    "item_id": "",
    "count": "1",
    "time": "2021-11-02 18:04:14",
    "name": "Harbinger of Dawn",
    "lang": "en-us",
    "item_type": "Weapon",
    "rank_type": "3",
    "id": "1635872760008201315"
   },
   {
    "uid": "700367142",
    "gacha_type": "302",
    "item_id": "",
    "count": "1",
    "time": "2021-11-02 18:04:14",
    "name": "Ferrous Shadow",
    "lang": "en-us",
    "item_type": "Weapon",
    "rank_type": "3",
    "id": "1635872760008201314"
   },
   {
    "uid": "700367142",
    "gacha_type": "302",
    "item_id": "",
    "count": "1",
    "time": "2021-10-03 14:36:11",
    "name": "Slingshot",
    "lang": "en-us",
    "item_type": "Weapon",
    "rank_type": "3",
    "id": "1633266360000875310"
   },
   {
    "uid": "700367142",
    "gacha_type": "302",
    "item_id": "",
    "count": "1",
    "time": "2021-10-03 14:36:11",
    "name": "Ferrous Shadow",
    "lang": "en-us",
    "item_type": "Weapon",
    "rank_type": "3",
    "id": "1633266360000875309"
   },
   {
    "uid": "700367142",
    "gacha_type": "302",
    "item_id": "",
    "count": "1",
    "time": "2021-10-03 14:36:11",
    "name": "Emerald Orb",
    "lang": "en-us",
    "item_type": "Weapon",
    "rank_type": "3",
    "id": "1633266360000875308"
   },
   {
    "uid": "700367142",
    "gacha_type": "302",
    "item_id": "",
    "count": "1",
    "time": "2021-10-03 14:36:11",
    "name": "Magic Guide",
    "lang": "en-us",
    "item_type": "Weapon",
    "rank_type": "3",
    "id": "1633266360000875307"
   },
   {
    "uid": "700367142",
    "gacha_type": "302",
    "item_id": "",
    "count": "1",
    "time": "2021-10-03 14:36:11",
    "name": "Harbinger of Dawn",
    "lang": "en-us",
    "item_type": "Weapon",
    "rank_type": "3",
    "id": "1633266360000875306"
   },
   {
    "uid": "700367142",
    "gacha_type": "302",
    "item_id": "",
    "count": "1",
    "time": "2021-10-03 14:36:11",
    "name": "Favonius Codex",
    "lang": "en-us",
    "item_type": "Weapon",
    "rank_type": "4",
    "id": "1633266360000875305"
   },
   {
    "uid": "700367142",
    "gacha_type": "302",
    "item_id": "",
    "count": "1",
    "time": "2021-10-03 14:36:11",
    "name": "Emerald Orb",
    "lang": "en-us",
    "item_type": "Weapon",
    "rank_type": "3",
    "id": "1633266360000875304"
   },
   {
    "uid": "700367142",
    "gacha_type": "302",
    "item_id": "",
    "count": "1",
    "time": "2021-10-03 14:36:11",
    "name": "Debate Club",
    "lang": "en-us",
    "item_type": "Weapon",
    "rank_type": "3",
    "id": "1633266360000875303"
   },
   {
    "uid": "700367142",
    "gacha_type": "302",
    "item_id": "",
    "count": "1",
    "time": "2021-10-03 14:36:11",
    "name": "Thrilling Tales of Dragon Slayers",
    "lang": "en-us",
    "item_type": "Weapon",
    "rank_type": "3",
    "id": "1633266360000875302"
   },
   {
    "uid": "700367142",
    "gacha_type": "302",
    "item_id": "",
    "count": "1",
    "time": "2021-10-03 14:36:11",
    "name": "Thrilling Tales of Dragon Slayers",
    "lang": "en-us",
    "item_type": "Weapon",
    "rank_type": "3",
    "id": "1633266360000875301"
   },
   {
    "uid": "700367142",
    "gacha_type": "302",
    "item_id": "",
    "count": "1",
    "time": "2021-09-26 11:21:32",
    "name": "Sharpshooter's Oath",
    "lang": "en-us",
    "item_type": "Weapon",
    "rank_type": "3",
    "id": "1632650760000122722"
   },
   {
    "uid": "700367142",
    "gacha_type": "302",
    "item_id": "",
    "count": "1",
    "time": "2021-07-28 19:57:29",
    "name": "Skyward Spine",
    "lang": "en-us",
    "item_type": "Weapon",
    "rank_type": "5",
    "id": "1627495560000345234"
   },
   {
    "uid": "700367142",
    "gacha_type": "302",
    "item_id": "",
    "count": "1",
    "time": "2021-07-28 19:57:21",
    "name": "Black Tassel",
    "lang": "en-us",
    "item_type": "Weapon",
    "rank_type": "3",
    "id": "1627495560000344550"
   },
   {
    "uid": "700367142",
    "gacha_type": "302",
    "item_id": "",
    "count": "1",
    "time": "2021-07-28 19:57:11",
    "name": "Sucrose",
    "lang": "en-us",
    "item_type": "Character",
    "rank_type": "4",
    "id": "1627495560000343416"
   },
   {
    "uid": "700367142",
    "gacha_type": "302",
    "item_id": "",
    "count": "1",
    "time": "2021-07-28 19:57:00",
    "name": "Harbinger of Dawn",
    "lang": "en-us",
    "item_type": "Weapon",
    "rank_type": "3",
    "id": "1627495560000342291"
   },
   {
    "uid": "700367142",
    "gacha_type": "302",
    "item_id": "",
    "count": "1",
    "time": "2021-07-23 13:22:25",
    "name": "Sacrificial Greatsword",
    "lang": "en-us",
    "item_type": "Weapon",
    "rank_type": "4",
    "id": "1627041960000175636"
   },
   {
    "uid": "700367142",
    "gacha_type": "302",
    "item_id": "",
    "count": "1",
    "time": "2021-07-23 13:22:17",
    "name": "Thrilling Tales of Dragon Slayers",
    "lang": "en-us",
    "item_type": "Weapon",
    "rank_type": "3",
    "id": "1627041960000174626"
   },
   {
    "uid": "700367142",
    "gacha_type": "302",
    "item_id": "",
    "count": "1",
    "time": "2021-07-23 13:22:10",
    "name": "Debate Club",
    "lang": "en-us",
    "item_type": "Weapon",
    "rank_type": "3",
    "id": "1627041960000173806"
   },
   {
    "uid": "700367142",
    "gacha_type": "302",
    "item_id": "",
    "count": "1",
    "time": "2021-07-23 13:22:03",
    "name": "Sharpshooter's Oath",
    "lang": "en-us",
    "item_type": "Weapon",
    "rank_type": "3",
    "id": "1627041960000172905"
   },
   {
    "uid": "700367142",
    "gacha_type": "302",
    "item_id": "",
    "count": "1",
    "time": "2021-07-23 13:21:17",
    "name": "Skyrider Sword",
    "lang": "en-us",
    "item_type": "Weapon",
    "rank_type": "3",
    "id": "1627041960000166852"
   },
   {
    "uid": "700367142",
    "gacha_type": "302",
    "item_id": "",
    "count": "1",
    "time": "2021-07-23 13:21:17",
    "name": "Raven Bow",
    "lang": "en-us",
    "item_type": "Weapon",
    "rank_type": "3",
    "id": "1627041960000166851"
   },
   {
    "uid": "700367142",
    "gacha_type": "302",
    "item_id": "",
    "count": "1",
    "time": "2021-07-23 13:21:17",
    "name": "Bloodtainted Greatsword",
    "lang": "en-us",
    "item_type": "Weapon",
    "rank_type": "3",
    "id": "1627041960000166850"
   },
   {
    "uid": "700367142",
    "gacha_type": "302",
    "item_id": "",
    "count": "1",
    "time": "2021-07-23 13:21:17",
    "name": "Slingshot",
    "lang": "en-us",
    "item_type": "Weapon",
    "rank_type": "3",
    "id": "1627041960000166849"
   },
   {
    "uid": "700367142",
    "gacha_type": "302",
    "item_id": "",
    "count": "1",
    "time": "2021-07-23 13:21:17",
    "name": "The Stringless",
    "lang": "en-us",
    "item_type": "Weapon",
    "rank_type": "4",
    "id": "1627041960000166848"
   },
   {
    "uid": "700367142",
    "gacha_type": "302",
    "item_id": "",
    "count": "1",
    "time": "2021-07-23 13:21:17",
    "name": "Thrilling Tales of Dragon Slayers",
    "lang": "en-us",
    "item_type": "Weapon",
    "rank_type": "3",
    "id": "1627041960000166847"
   },
   {
    "uid": "700367142",
    "gacha_type": "302",
    "item_id": "",
    "count": "1",
    "time": "2021-07-23 13:21:17",
    "name": "Slingshot",
    "lang": "en-us",
    "item_type": "Weapon",
    "rank_type": "3",
    "id": "1627041960000166846"
   },
   {
    "uid": "700367142",
    "gacha_type": "302",
    "item_id": "",
    "count": "1",
    "time": "2021-07-23 13:21:17",
    "name": "Magic Guide",
    "lang": "en-us",
    "item_type": "Weapon",
    "rank_type": "3",
    "id": "1627041960000166845"
   },
   {
    "uid": "700367142",
    "gacha_type": "302",
    "item_id": "",
    "count": "1",
    "time": "2021-07-23 13:21:17",
    "name": "Ferrous Shadow",
    "lang": "en-us",
    "item_type": "Weapon",
    "rank_type": "3",
    "id": "1627041960000166844"
   },
   {
    "uid": "700367142",
    "gacha_type": "302",
    "item_id": "",
    "count": "1",
    "time": "2021-07-23 13:21:17",
    "name": "Favonius Sword",
    "lang": "en-us",
    "item_type": "Weapon",
    "rank_type": "4",
    "id": "1627041960000166843"
   },
   {
    "uid": "700367142",
    "gacha_type": "302",
    "item_id": "",
    "count": "1",
    "time": "2021-07-22 07:51:07",
    "name": "Bloodtainted Greatsword",
    "lang": "en-us",
    "item_type": "Weapon",
    "rank_type": "3",
    "id": "1626933960000181606"
   },
   {
    "uid": "700367142",
    "gacha_type": "302",
    "item_id": "",
    "count": "1",
    "time": "2021-07-22 07:50:59",
    "name": "Slingshot",
    "lang": "en-us",
    "item_type": "Weapon",
    "rank_type": "3",
    "id": "1626933960000180994"
   },
   {
    "uid": "700367142",
    "gacha_type": "302",
    "item_id": "",
    "count": "1",
    "time": "2021-07-22 07:50:50",
    "name": "Razor",
    "lang": "en-us",
    "item_type": "Character",
    "rank_type": "4",
    "id": "1626933960000180225"
   },
   {
    "uid": "700367142",
    "gacha_type": "302",
    "item_id": "",
    "count": "1",
    "time": "2021-07-22 07:50:41",
    "name": "Magic Guide",
    "lang": "en-us",
    "item_type": "Weapon",
    "rank_type": "3",
    "id": "1626933960000179551"
   },
   {
    "uid": "700367142",
    "gacha_type": "302",
    "item_id": "",
    "count": "1",
    "time": "2021-07-21 07:22:05",
    "name": "Sharpshooter's Oath",
    "lang": "en-us",
    "item_type": "Weapon",
    "rank_type": "3",
    "id": "1626847560000547028"
   },
   {
    "uid": "700367142",
    "gacha_type": "302",
    "item_id": "",
    "count": "1",
    "time": "2021-07-21 07:22:05",
    "name": "Debate Club",
    "lang": "en-us",
    "item_type": "Weapon",
    "rank_type": "3",
    "id": "1626847560000547027"
   },
   {
    "uid": "700367142",
    "gacha_type": "302",
    "item_id": "",
    "count": "1",
    "time": "2021-07-21 07:22:05",
    "name": "Harbinger of Dawn",
    "lang": "en-us",
    "item_type": "Weapon",
    "rank_type": "3",
    "id": "1626847560000547026"
   },
   {
    "uid": "700367142",
    "gacha_type": "302",
    "item_id": "",
    "count": "1",
    "time": "2021-07-21 07:22:05",
    "name": "Emerald Orb",
    "lang": "en-us",
    "item_type": "Weapon",
    "rank_type": "3",
    "id": "1626847560000547025"
   },
   {
    "uid": "700367142",
    "gacha_type": "302",
    "item_id": "",
    "count": "1",
    "time": "2021-07-21 07:22:05",
    "name": "Slingshot",
    "lang": "en-us",
    "item_type": "Weapon",
    "rank_type": "3",
    "id": "1626847560000547024"
   },
   {
    "uid": "700367142",
    "gacha_type": "302",
    "item_id": "",
    "count": "1",
    "time": "2021-07-21 07:22:05",
    "name": "Sharpshooter's Oath",
    "lang": "en-us",
    "item_type": "Weapon",
    "rank_type": "3",
    "id": "1626847560000547023"
   },
   {
    "uid": "700367142",
    "gacha_type": "302",
    "item_id": "",
    "count": "1",
    "time": "2021-07-21 07:22:05",
    "name": "Favonius Codex",
    "lang": "en-us",
    "item_type": "Weapon",
    "rank_type": "4",
    "id": "1626847560000547022"
   },
   {
    "uid": "700367142",
    "gacha_type": "302",
    "item_id": "",
    "count": "1",
    "time": "2021-07-21 07:22:05",
    "name": "Emerald Orb",
    "lang": "en-us",
    "item_type": "Weapon",
    "rank_type": "3",
    "id": "1626847560000547021"
   },
   {
    "uid": "700367142",
    "gacha_type": "302",
    "item_id": "",
    "count": "1",
    "time": "2021-07-21 07:22:05",
    "name": "Magic Guide",
    "lang": "en-us",
    "item_type": "Weapon",
    "rank_type": "3",
    "id": "1626847560000547020"
   },
   {
    "uid": "700367142",
    "gacha_type": "302",
    "item_id": "",
    "count": "1",
    "time": "2021-07-21 07:22:05",
    "name": "Skyrider Sword",
    "lang": "en-us",
    "item_type": "Weapon",
    "rank_type": "3",
    "id": "1626847560000547019"
   },
   {
    "uid": "700367142",
    "gacha_type": "302",
    "item_id": "",
    "count": "1",
    "time": "2021-07-21 05:09:36",
    "name": "Thrilling Tales of Dragon Slayers",
    "lang": "en-us",
    "item_type": "Weapon",
    "rank_type": "3",
    "id": "1626840360000194921"
   },
   {
    "uid": "700367142",
    "gacha_type": "302",
    "item_id": "",
    "count": "1",
    "time": "2021-07-21 05:09:36",
    "name": "Debate Club",
    "lang": "en-us",
    "item_type": "Weapon",
    "rank_type": "3",
    "id": "1626840360000194920"
   },
   {
    "uid": "700367142",
    "gacha_type": "302",
    "item_id": "",
    "count": "1",
    "time": "2021-07-21 05:09:36",
    "name": "Bennett",
    "lang": "en-us",
    "item_type": "Character",
    "rank_type": "4",
    "id": "1626840360000194919"
   },
   {
    "uid": "700367142",
    "gacha_type": "302",
    "item_id": "",
    "count": "1",
    "time": "2021-07-21 05:09:36",
    "name": "Magic Guide",
    "lang": "en-us",
    "item_type": "Weapon",
    "rank_type": "3",
    "id": "1626840360000194918"
   },
   {
    "uid": "700367142",
    "gacha_type": "302",
    "item_id": "",
    "count": "1",
    "time": "2021-07-21 05:09:36",
    "name": "Slingshot",
    "lang": "en-us",
    "item_type": "Weapon",
    "rank_type": "3",
    "id": "1626840360000194917"
   },
   {
    "uid": "700367142",
    "gacha_type": "302",
    "item_id": "",
    "count": "1",
    "time": "2021-07-21 05:09:36",
    "name": "Emerald Orb",
    "lang": "en-us",
    "item_type": "Weapon",
    "rank_type": "3",
    "id": "1626840360000194916"
   },
   {
    "uid": "700367142",
    "gacha_type": "302",
    "item_id": "",
    "count": "1",
    "time": "2021-07-21 05:09:36",
    "name": "Ferrous Shadow",
    "lang": "en-us",
    "item_type": "Weapon",
    "rank_type": "3",
    "id": "1626840360000194915"
   },
   {
    "uid": "700367142",
    "gacha_type": "302",
    "item_id": "",
    "count": "1",
    "time": "2021-07-21 05:09:36",
    "name": "Thrilling Tales of Dragon Slayers",
    "lang": "en-us",
    "item_type": "Weapon",
    "rank_type": "3",
    "id": "1626840360000194914"
   },
   {
    "uid": "700367142",
    "gacha_type": "302",
    "item_id": "",
    "count": "1",
    "time": "2021-07-21 05:09:36",
    "name": "Sharpshooter's Oath",
    "lang": "en-us",
    "item_type": "Weapon",
    "rank_type": "3",
    "id": "1626840360000194913"
   },
   {
    "uid": "700367142",
    "gacha_type": "302",
    "item_id": "",
    "count": "1",
    "time": "2021-07-21 05:09:36",
    "name": "Favonius Sword",
    "lang": "en-us",
    "item_type": "Weapon",
    "rank_type": "4",
    "id": "1626840360000194912"
   },
   {
    "uid": "700367142",
    "gacha_type": "302",
    "item_id": "",
    "count": "1",
    "time": "2021-07-21 05:08:44",
    "name": "Thrilling Tales of Dragon Slayers",
    "lang": "en-us",
    "item_type": "Weapon",
    "rank_type": "3",
    "id": "1626840360000177597"
   },
   {
    "uid": "700367142",
    "gacha_type": "302",
    "item_id": "",
    "count": "1",
    "time": "2021-07-21 05:08:44",
    "name": "Slingshot",
    "lang": "en-us",
    "item_type": "Weapon",
    "rank_type": "3",
    "id": "1626840360000177596"
   },
   {
    "uid": "700367142",
    "gacha_type": "302",
    "item_id": "",
    "count": "1",
    "time": "2021-07-21 05:08:44",
    "name": "Sharpshooter's Oath",
    "lang": "en-us",
    "item_type": "Weapon",
    "rank_type": "3",
    "id": "1626840360000177595"
   },
   {
    "uid": "700367142",
    "gacha_type": "302",
    "item_id": "",
    "count": "1",
    "time": "2021-07-21 05:08:44",
    "name": "Debate Club",
    "lang": "en-us",
    "item_type": "Weapon",
    "rank_type": "3",
    "id": "1626840360000177594"
   },
   {
    "uid": "700367142",
    "gacha_type": "302",
    "item_id": "",
    "count": "1",
    "time": "2021-07-21 05:08:44",
    "name": "Thrilling Tales of Dragon Slayers",
    "lang": "en-us",
    "item_type": "Weapon",
    "rank_type": "3",
    "id": "1626840360000177593"
   },
   {
    "uid": "700367142",
    "gacha_type": "302",
    "item_id": "",
    "count": "1",
    "time": "2021-07-21 05:08:44",
    "name": "Harbinger of Dawn",
    "lang": "en-us",
    "item_type": "Weapon",
    "rank_type": "3",
    "id": "1626840360000177592"
   },
   {
    "uid": "700367142",
    "gacha_type": "302",
    "item_id": "",
    "count": "1",
    "time": "2021-07-21 05:08:44",
    "name": "Black Tassel",
    "lang": "en-us",
    "item_type": "Weapon",
    "rank_type": "3",
    "id": "1626840360000177591"
   },
   {
    "uid": "700367142",
    "gacha_type": "302",
    "item_id": "",
    "count": "1",
    "time": "2021-07-21 05:08:44",
    "name": "Ferrous Shadow",
    "lang": "en-us",
    "item_type": "Weapon",
    "rank_type": "3",
    "id": "1626840360000177590"
   },
   {
    "uid": "700367142",
    "gacha_type": "302",
    "item_id": "",
    "count": "1",
    "time": "2021-07-21 05:08:44",
    "name": "Favonius Sword",
    "lang": "en-us",
    "item_type": "Weapon",
    "rank_type": "4",
    "id": "1626840360000177589"
   },
   {
    "uid": "700367142",
    "gacha_type": "302",
    "item_id": "",
    "count": "1",
    "time": "2021-07-21 05:08:44",
    "name": "Slingshot",
    "lang": "en-us",
    "item_type": "Weapon",
    "rank_type": "3",
    "id": "1626840360000177588"
   },
   {
    "uid": "700367142",
    "gacha_type": "302",
    "item_id": "",
    "count": "1",
    "time": "2021-06-23 20:14:51",
    "name": "Magic Guide",
    "lang": "en-us",
    "item_type": "Weapon",
    "rank_type": "3",
    "id": "1624475160000045100"
   }
  ]
 },
 "100": {
  "total": 20,
  "list": []
 },
 "200": {
  "total": 120,
  "list": [
   {
    "uid": "700367142",
    "gacha_type": "200",
    "item_id": "",
    "count": "1",
    "time": "2021-11-21 19:50:44",
    "name": "Cool Steel",
    "lang": "en-us",
    "item_type": "Weapon",
    "rank_type": "3",
    "id": "1637517960000203814"
   },
   {
    "uid": "700367142",
    "gacha_type": "200",
    "item_id": "",
    "count": "1",
    "time": "2021-11-21 08:16:55",
    "name": "Emerald Orb",
    "lang": "en-us",
    "item_type": "Weapon",
    "rank_type": "3",
    "id": "1637478360000026893"
   },
   {
    "uid": "700367142",
    "gacha_type": "200",
    "item_id": "",
    "count": "1",
    "time": "2021-11-14 15:26:12",
    "name": "Diona",
    "lang": "en-us",
    "item_type": "Character",
    "rank_type": "4",
    "id": "1636898760000138322"
   },
   {
    "uid": "700367142",
    "gacha_type": "200",
    "item_id": "",
    "count": "1",
    "time": "2021-11-07 11:46:48",
    "name": "Magic Guide",
    "lang": "en-us",
    "item_type": "Weapon",
    "rank_type": "3",
    "id": "1636279560000297867"
   },
   {
    "uid": "700367142",
    "gacha_type": "200",
    "item_id": "",
    "count": "1",
    "time": "2021-11-03 12:08:01",
    "name": "Debate Club",
    "lang": "en-us",
    "item_type": "Weapon",
    "rank_type": "3",
    "id": "1635937560000120460"
   },
   {
    "uid": "700367142",
    "gacha_type": "200",
    "item_id": "",
    "count": "1",
    "time": "2021-11-02 18:22:38",
    "name": "Magic Guide",
    "lang": "en-us",
    "item_type": "Weapon",
    "rank_type": "3",
    "id": "1635872760027626679"
   },
   {
    "uid": "700367142",
    "gacha_type": "200",
    "item_id": "",
    "count": "1",
    "time": "2021-11-02 18:08:04",
    "name": "Debate Club",
    "lang": "en-us",
    "item_type": "Weapon",
    "rank_type": "3",
    "id": "1635872760014548618"
   },
   {
    "uid": "700367142",
    "gacha_type": "200",
    "item_id": "",
    "count": "1",
    "time": "2021-11-02 18:07:23",
    "name": "Sharpshooter's Oath",
    "lang": "en-us",
    "item_type": "Weapon",
    "rank_type": "3",
    "id": "1635872760013572084"
   },
   {
    "uid": "700367142",
    "gacha_type": "200",
    "item_id": "",
    "count": "1",
    "time": "2021-11-02 18:07:16",
    "name": "Debate Club",
    "lang": "en-us",
    "item_type": "Weapon",
    "rank_type": "3",
    "id": "1635872760013397609"
   },
   {
    "uid": "700367142",
    "gacha_type": "200",
    "item_id": "",
    "count": "1",
    "time": "2021-11-02 18:07:09",
    "name": "Debate Club",
    "lang": "en-us",
    "item_type": "Weapon",
    "rank_type": "3",
    "id": "1635872760013224649"
   },
   {
    "uid": "700367142",
    "gacha_type": "200",
    "item_id": "",
    "count": "1",
    "time": "2021-10-30 17:35:50",
    "name": "Sharpshooter's Oath",
    "lang": "en-us",
    "item_type": "Weapon",
    "rank_type": "3",
    "id": "1635609960000143397"
   },
   {
    "uid": "700367142",
    "gacha_type": "200",
    "item_id": "",
    "count": "1",
    "time": "2021-10-25 20:29:19",
    "name": "Harbinger of Dawn",
    "lang": "en-us",
    "item_type": "Weapon",
    "rank_type": "3",
    "id": "1635188760000115049"
   },
   {
    "uid": "700367142",
    "gacha_type": "200",
    "item_id": "",
    "count": "1",
    "time": "2021-10-13 07:21:54",
    "name": "Rainslasher",
    "lang": "en-us",
    "item_type": "Weapon",
    "rank_type": "4",
    "id": "1634105160000894697"
   },
   {
    "uid": "700367142",
    "gacha_type": "200",
    "item_id": "",
    "count": "1",
    "time": "2021-10-13 07:21:47",
    "name": "Magic Guide",
    "lang": "en-us",
    "item_type": "Weapon",
    "rank_type": "3",
    "id": "1634105160000889662"
   },
   {
    "uid": "700367142",
    "gacha_type": "200",
    "item_id": "",
    "count": "1",
    "time": "2021-10-04 06:46:04",
    "name": "Debate Club",
    "lang": "en-us",
    "item_type": "Weapon",
    "rank_type": "3",
    "id": "1633323960000460889"
   },
   {
    "uid": "700367142",
    "gacha_type": "200",
    "item_id": "",
    "count": "1",
    "time": "2021-09-28 19:33:34",
    "name": "Xingqiu",
    "lang": "en-us",
    "item_type": "Character",
    "rank_type": "4",
    "id": "1632852360000201962"
   },
   {
    "uid": "700367142",
    "gacha_type": "200",
    "item_id": "",
    "count": "1",
    "time": "2021-09-28 06:10:16",
    "name": "Emerald Orb",
    "lang": "en-us",
    "item_type": "Weapon",
    "rank_type": "3",
    "id": "1632805560000024705"
   },
   {
    "uid": "700367142",
    "gacha_type": "200",
    "item_id": "",
    "count": "1",
    "time": "2021-09-17 14:18:30",
    "name": "Emerald Orb",
    "lang": "en-us",
    "item_type": "Weapon",
    "rank_type": "3",
    "id": "1631883960000119380"
   },
   {
    "uid": "700367142",
    "gacha_type": "200",
    "item_id": "",
    "count": "1",
    "time": "2021-09-16 20:54:57",
    "name": "Wolf's Gravestone",
    "lang": "en-us",
    "item_type": "Weapon",
    "rank_type": "5",
    "id": "1631819160000369987"
   },
   {
    "uid": "700367142",
    "gacha_type": "200",
    "item_id": "",
    "count": "1",
    "time": "2021-09-11 11:22:36",
    "name": "Ferrous Shadow",
    "lang": "en-us",
    "item_type": "Weapon",
    "rank_type": "3",
    "id": "1631354760000177744"
   },
   {
    "uid": "700367142",
    "gacha_type": "200",
    "item_id": "",
    "count": "1",
    "time": "2021-09-06 16:27:07",
    "name": "Cool Steel",
    "lang": "en-us",
    "item_type": "Weapon",
    "rank_type": "3",
    "id": "1630940760000226001"
   },
   {
    "uid": "700367142",
    "gacha_type": "200",
    "item_id": "",
    "count": "1",
    "time": "2021-09-06 10:47:49",
    "name": "Slingshot",
    "lang": "en-us",
    "item_type": "Weapon",
    "rank_type": "3",
    "id": "1630919160000233165"
   },
   {
    "uid": "700367142",
    "gacha_type": "200",
    "item_id": "",
    "count": "1",
    "time": "2021-09-06 10:47:42",
    "name": "Ferrous Shadow",
    "lang": "en-us",
    "item_type": "Weapon",
    "rank_type": "3",
    "id": "1630919160000232544"
   },
   {
    "uid": "700367142",
    "gacha_type": "200",
    "item_id": "",
    "count": "1",
    "time": "2021-09-05 18:56:10",
    "name": "Black Tassel",
    "lang": "en-us",
    "item_type": "Weapon",
    "rank_type": "3",
    "id": "1630861560000516022"
   },
   {
    "uid": "700367142",
    "gacha_type": "200",
    "item_id": "",
    "count": "1",
    "time": "2021-09-05 07:40:51",
    "name": "Debate Club",
    "lang": "en-us",
    "item_type": "Weapon",
    "rank_type": "3",
    "id": "1630821960000136889"
   },
   {
    "uid": "700367142",
    "gacha_type": "200",
    "item_id": "",
    "count": "1",
    "time": "2021-09-05 07:40:32",
    "name": "The Bell",
    "lang": "en-us",
    "item_type": "Weapon",
    "rank_type": "4",
    "id": "1630821960000135678"
   },
   {
    "uid": "700367142",
    "gacha_type": "200",
    "item_id": "",
    "count": "1",
    "time": "2021-09-05 07:40:27",
    "name": "Cool Steel",
    "lang": "en-us",
    "item_type": "Weapon",
    "rank_type": "3",
    "id": "1630821960000135386"
   },
   {
    "uid": "700367142",
    "gacha_type": "200",
    "item_id": "",
    "count": "1",
    "time": "2021-09-05 07:40:21",
    "name": "Bloodtainted Greatsword",
    "lang": "en-us",
    "item_type": "Weapon",
    "rank_type": "3",
    "id": "1630821960000135050"
   },
   {
    "uid": "700367142",
    "gacha_type": "200",
    "item_id": "",
    "count": "1",
    "time": "2021-09-05 07:38:40",
    "name": "Xingqiu",
    "lang": "en-us",
    "item_type": "Character",
    "rank_type": "4",
    "id": "1630821960000128734"
   },
   {
    "uid": "700367142",
    "gacha_type": "200",
    "item_id": "",
    "count": "1",
    "time": "2021-09-04 19:16:41",
    "name": "Black Tassel",
    "lang": "en-us",
    "item_type": "Weapon",
    "rank_type": "3",
    "id": "1630778760000160079"
   },
   {
    "uid": "700367142",
    "gacha_type": "200",
    "item_id": "",
    "count": "1",
    "time": "2021-09-04 19:16:33",
    "name": "Cool Steel",
    "lang": "en-us",
    "item_type": "Weapon",
    "rank_type": "3",
    "id": "1630778760000158673"
   },
   {
    "uid": "700367142",
    "gacha_type": "200",
    "item_id": "",
    "count": "1",
    "time": "2021-09-04 10:37:05",
    "name": "Sharpshooter's Oath",
    "lang": "en-us",
    "item_type": "Weapon",
    "rank_type": "3",
    "id": "1630746360000304159"
   },
   {
    "uid": "700367142",
    "gacha_type": "200",
    "item_id": "",
    "count": "1",
    "time": "2021-09-03 20:09:57",
    "name": "Black Tassel",
    "lang": "en-us",
    "item_type": "Weapon",
    "rank_type": "3",
    "id": "1630695960000115246"
   },
   {
    "uid": "700367142",
    "gacha_type": "200",
    "item_id": "",
    "count": "1",
    "time": "2021-09-01 19:38:04",
    "name": "Skyrider Sword",
    "lang": "en-us",
    "item_type": "Weapon",
    "rank_type": "3",
    "id": "1630519560001527577"
   },
   {
    "uid": "700367142",
    "gacha_type": "200",
    "item_id": "",
    "count": "1",
    "time": "2021-09-01 19:37:55",
    "name": "Sucrose",
    "lang": "en-us",
    "item_type": "Character",
    "rank_type": "4",
    "id": "1630519560001521847"
   },
   {
    "uid": "700367142",
    "gacha_type": "200",
    "item_id": "",
    "count": "1",
    "time": "2021-08-22 21:50:17",
    "name": "Slingshot",
    "lang": "en-us",
    "item_type": "Weapon",
    "rank_type": "3",
    "id": "1629662760000264384"
   },
   {
    "uid": "700367142",
    "gacha_type": "200",
    "item_id": "",
    "count": "1",
    "time": "2021-08-22 21:30:43",
    "name": "Bloodtainted Greatsword",
    "lang": "en-us",
    "item_type": "Weapon",
    "rank_type": "3",
    "id": "1629662760000154625"
   },
   {
    "uid": "700367142",
    "gacha_type": "200",
    "item_id": "",
    "count": "1",
    "time": "2021-08-21 19:21:46",
    "name": "Ferrous Shadow",
    "lang": "en-us",
    "item_type": "Weapon",
    "rank_type": "3",
    "id": "1629569160000115777"
   },
   {
    "uid": "700367142",
    "gacha_type": "200",
    "item_id": "",
    "count": "1",
    "time": "2021-08-17 10:02:48",
    "name": "Raven Bow",
    "lang": "en-us",
    "item_type": "Weapon",
    "rank_type": "3",
    "id": "1629191160000009328"
   },
   {
    "uid": "700367142",
    "gacha_type": "200",
    "item_id": "",
    "count": "1",
    "time": "2021-08-15 21:16:06",
    "name": "Harbinger of Dawn",
    "lang": "en-us",
    "item_type": "Weapon",
    "rank_type": "3",
    "id": "1629057960000084781"
   },
   {
    "uid": "700367142",
    "gacha_type": "200",
    "item_id": "",
    "count": "1",
    "time": "2021-08-11 20:14:42",
    "name": "Debate Club",
    "lang": "en-us",
    "item_type": "Weapon",
    "rank_type": "3",
    "id": "1628708760000109519"
   },
   {
    "uid": "700367142",
    "gacha_type": "200",
    "item_id": "",
    "count": "1",
    "time": "2021-08-10 08:01:24",
    "name": "Debate Club",
    "lang": "en-us",
    "item_type": "Weapon",
    "rank_type": "3",
    "id": "1628579160000002877"
   },
   {
    "uid": "700367142",
    "gacha_type": "200",
    "item_id": "",
    "count": "1",
    "time": "2021-08-09 19:39:45",
    "name": "Emerald Orb",
    "lang": "en-us",
    "item_type": "Weapon",
    "rank_type": "3",
    "id": "1628532360000207887"
   },
   {
    "uid": "700367142",
    "gacha_type": "200",
    "item_id": "",
    "count": "1",
    "time": "2021-08-04 10:10:08",
    "name": "Emerald Orb",
    "lang": "en-us",
    "item_type": "Weapon",
    "rank_type": "3",
    "id": "1628067960000052526"
   },
   {
    "uid": "700367142",
    "gacha_type": "200",
    "item_id": "",
    "count": "1",
    "time": "2021-08-01 16:51:47",
    "name": "The Bell",
    "lang": "en-us",
    "item_type": "Weapon",
    "rank_type": "4",
    "id": "1627830360000546964"
   },
   {
    "uid": "700367142",
    "gacha_type": "200",
    "item_id": "",
    "count": "1",
    "time": "2021-08-01 16:50:33",
    "name": "Skyrider Sword",
    "lang": "en-us",
    "item_type": "Weapon",
    "rank_type": "3",
    "id": "1627830360000534736"
   },
   {
    "uid": "700367142",
    "gacha_type": "200",
    "item_id": "",
    "count": "1",
    "time": "2021-08-01 16:50:24",
    "name": "Thrilling Tales of Dragon Slayers",
    "lang": "en-us",
    "item_type": "Weapon",
    "rank_type": "3",
    "id": "1627830360000533160"
   },
   {
    "uid": "700367142",
    "gacha_type": "200",
    "item_id": "",
    "count": "1",
    "time": "2021-08-01 10:34:47",
    "name": "Bloodtainted Greatsword",
    "lang": "en-us",
    "item_type": "Weapon",
    "rank_type": "3",
    "id": "1627808760000452550"
   },
   {
    "uid": "700367142",
    "gacha_type": "200",
    "item_id": "",
    "count": "1",
    "time": "2021-07-27 21:09:57",
    "name": "Raven Bow",
    "lang": "en-us",
    "item_type": "Weapon",
    "rank_type": "3",
    "id": "1627416360000067042"
   },
   {
    "uid": "700367142",
    "gacha_type": "200",
    "item_id": "",
    "count": "1",
    "time": "2021-07-27 21:09:50",
    "name": "Debate Club",
    "lang": "en-us",
    "item_type": "Weapon",
    "rank_type": "3",
    "id": "1627416360000066242"
   },
   {
    "uid": "700367142",
    "gacha_type": "200",
    "item_id": "",
    "count": "1",
    "time": "2021-07-24 20:45:40",
    "name": "Raven Bow",
    "lang": "en-us",
    "item_type": "Weapon",
    "rank_type": "3",
    "id": "1627153560000436638"
   },
   {
    "uid": "700367142",
    "gacha_type": "200",
    "item_id": "",
    "count": "1",
    "time": "2021-07-24 19:00:00",
    "name": "Raven Bow",
    "lang": "en-us",
    "item_type": "Weapon",
    "rank_type": "3",
    "id": "1627149960000000003"
   },
   {
    "uid": "700367142",
    "gacha_type": "200",
    "item_id": "",
    "count": "1",
    "time": "2021-07-24 14:37:09",
    "name": "Cool Steel",
    "lang": "en-us",
    "item_type": "Weapon",
    "rank_type": "3",
    "id": "1627131960000269105"
   },
   {
    "uid": "700367142",
    "gacha_type": "200",
    "item_id": "",
    "count": "1",
    "time": "2021-07-24 08:08:55",
    "name": "Lisa",
    "lang": "en-us",
    "item_type": "Character",
    "rank_type": "4",
    "id": "1627110360000028982"
   },
   {
    "uid": "700367142",
    "gacha_type": "200",
    "item_id": "",
    "count": "1",
    "time": "2021-07-24 08:08:45",
    "name": "Emerald Orb",
    "lang": "en-us",
    "item_type": "Weapon",
    "rank_type": "3",
    "id": "1627110360000028471"
   },
   {
    "uid": "700367142",
    "gacha_type": "200",
    "item_id": "",
    "count": "1",
    "time": "2021-07-22 20:47:43",
    "name": "Emerald Orb",
    "lang": "en-us",
    "item_type": "Weapon",
    "rank_type": "3",
    "id": "1626980760000489439"
   },
   {
    "uid": "700367142",
    "gacha_type": "200",
    "item_id": "",
    "count": "1",
    "time": "2021-07-22 20:47:34",
    "name": "Harbinger of Dawn",
    "lang": "en-us",
    "item_type": "Weapon",
    "rank_type": "3",
    "id": "1626980760000487816"
   },
   {
    "uid": "700367142",
    "gacha_type": "200",
    "item_id": "",
    "count": "1",
    "time": "2021-07-22 11:17:58",
    "name": "Xiangling",
    "lang": "en-us",
    "item_type": "Character",
    "rank_type": "4",
    "id": "1626948360000154467"
   },
   {
    "uid": "700367142",
    "gacha_type": "200",
    "item_id": "",
    "count": "1",
    "time": "2021-07-21 21:25:45",
    "name": "Sharpshooter's Oath",
    "lang": "en-us",
    "item_type": "Weapon",
    "rank_type": "3",
    "id": "1626897960000397025"
   },
   {
    "uid": "700367142",
    "gacha_type": "200",
    "item_id": "",
    "count": "1",
    "time": "2021-07-21 21:25:45",
    "name": "Skyrider Sword",
    "lang": "en-us",
    "item_type": "Weapon",
    "rank_type": "3",
    "id": "1626897960000397024"
   },
   {
    "uid": "700367142",
    "gacha_type": "200",
    "item_id": "",
    "count": "1",
    "time": "2021-07-21 21:25:45",
    "name": "Sharpshooter's Oath",
    "lang": "en-us",
    "item_type": "Weapon",
    "rank_type": "3",
    "id": "1626897960000397023"
   },
   {
    "uid": "700367142",
    "gacha_type": "200",
    "item_id": "",
    "count": "1",
    "time": "2021-07-21 21:25:45",
    "name": "Skyrider Sword",
    "lang": "en-us",
    "item_type": "Weapon",
    "rank_type": "3",
    "id": "1626897960000397022"
   },
   {
    "uid": "700367142",
    "gacha_type": "200",
    "item_id": "",
    "count": "1",
    "time": "2021-07-21 21:25:45",
    "name": "Bloodtainted Greatsword",
    "lang": "en-us",
    "item_type": "Weapon",
    "rank_type": "3",
    "id": "1626897960000397021"
   },
   {
    "uid": "700367142",
    "gacha_type": "200",
    "item_id": "",
    "count": "1",
    "time": "2021-07-21 21:25:45",
    "name": "Debate Club",
    "lang": "en-us",
    "item_type": "Weapon",
    "rank_type": "3",
    "id": "1626897960000397020"
   },
   {
    "uid": "700367142",
    "gacha_type": "200",
    "item_id": "",
    "count": "1",
    "time": "2021-07-21 21:25:45",
    "name": "Sharpshooter's Oath",
    "lang": "en-us",
    "item_type": "Weapon",
    "rank_type": "3",
    "id": "1626897960000397019"
   },
   {
    "uid": "700367142",
    "gacha_type": "200",
    "item_id": "",
    "count": "1",
    "time": "2021-07-21 21:25:45",
    "name": "Debate Club",
    "lang": "en-us",
    "item_type": "Weapon",
    "rank_type": "3",
    "id": "1626897960000397018"
   },
   {
    "uid": "700367142",
    "gacha_type": "200",
    "item_id": "",
    "count": "1",
    "time": "2021-07-21 21:25:45",
    "name": "Emerald Orb",
    "lang": "en-us",
    "item_type": "Weapon",
    "rank_type": "3",
    "id": "1626897960000397017"
   },
   {
    "uid": "700367142",
    "gacha_type": "200",
    "item_id": "",
    "count": "1",
    "time": "2021-07-21 21:25:45",
    "name": "The Bell",
    "lang": "en-us",
    "item_type": "Weapon",
    "rank_type": "4",
    "id": "1626897960000397016"
   },
   {
    "uid": "700367142",
    "gacha_type": "200",
    "item_id": "",
    "count": "1",
    "time": "2021-07-06 10:35:53",
    "name": "Raven Bow",
    "lang": "en-us",
    "item_type": "Weapon",
    "rank_type": "3",
    "id": "1625562360000138070"
   },
   {
    "uid": "700367142",
    "gacha_type": "200",
    "item_id": "",
    "count": "1",
    "time": "2021-07-05 15:26:41",
    "name": "Black Tassel",
    "lang": "en-us",
    "item_type": "Weapon",
    "rank_type": "3",
    "id": "1625493960000132476"
   },
   {
    "uid": "700367142",
    "gacha_type": "200",
    "item_id": "",
    "count": "1",
    "time": "2021-06-22 18:33:09",
    "name": "Magic Guide",
    "lang": "en-us",
    "item_type": "Weapon",
    "rank_type": "3",
    "id": "1624381560000114892"
   },
   {
    "uid": "700367142",
    "gacha_type": "200",
    "item_id": "",
    "count": "1",
    "time": "2021-06-22 18:33:02",
    "name": "Harbinger of Dawn",
    "lang": "en-us",
    "item_type": "Weapon",
    "rank_type": "3",
    "id": "1624381560000114497"
   },
   {
    "uid": "700367142",
    "gacha_type": "200",
    "item_id": "",
    "count": "1",
    "time": "2021-06-22 18:32:57",
    "name": "Raven Bow",
    "lang": "en-us",
    "item_type": "Weapon",
    "rank_type": "3",
    "id": "1624381560000114184"
   },
   {
    "uid": "700367142",
    "gacha_type": "200",
    "item_id": "",
    "count": "1",
    "time": "2021-06-22 18:32:49",
    "name": "Ferrous Shadow",
    "lang": "en-us",
    "item_type": "Weapon",
    "rank_type": "3",
    "id": "1624381560000113705"
   },
   {
    "uid": "700367142",
    "gacha_type": "200",
    "item_id": "",
    "count": "1",
    "time": "2021-06-20 20:39:16",
    "name": "Harbinger of Dawn",
    "lang": "en-us",
    "item_type": "Weapon",
    "rank_type": "3",
    "id": "1624215960000144821"
   },
   {
    "uid": "700367142",
    "gacha_type": "200",
    "item_id": "",
    "count": "1",
    "time": "2021-06-14 19:46:43",
    "name": "Black Tassel",
    "lang": "en-us",
    "item_type": "Weapon",
    "rank_type": "3",
    "id": "1623693960000225680"
   },
   {
    "uid": "700367142",
    "gacha_type": "200",
    "item_id": "",
    "count": "1",
    "time": "2021-06-03 13:10:07",
    "name": "Cool Steel",
    "lang": "en-us",
    "item_type": "Weapon",
    "rank_type": "3",
    "id": "1622721960000032929"
   },
   {
    "uid": "700367142",
    "gacha_type": "200",
    "item_id": "",
    "count": "1",
    "time": "2021-05-24 22:49:30",
    "name": "Amber",
    "lang": "en-us",
    "item_type": "Character",
    "rank_type": "4",
    "id": "1621890360000135808"
   },
   {
    "uid": "700367142",
    "gacha_type": "200",
    "item_id": "",
    "count": "1",
    "time": "2021-05-24 22:48:50",
    "name": "Harbinger of Dawn",
    "lang": "en-us",
    "item_type": "Weapon",
    "rank_type": "3",
    "id": "1621890360000134192"
   },
   {
    "uid": "700367142",
    "gacha_type": "200",
    "item_id": "",
    "count": "1",
    "time": "2021-05-24 22:48:01",
    "name": "Bloodtainted Greatsword",
    "lang": "en-us",
    "item_type": "Weapon",
    "rank_type": "3",
    "id": "1621890360000132183"
   },
   {
    "uid": "700367142",
    "gacha_type": "200",
    "item_id": "",
    "count": "1",
    "time": "2021-05-24 22:47:53",
    "name": "Harbinger of Dawn",
    "lang": "en-us",
    "item_type": "Weapon",
    "rank_type": "3",
    "id": "1621890360000131817"
   },
   {
    "uid": "700367142",
    "gacha_type": "200",
    "item_id": "",
    "count": "1",
    "time": "2021-05-24 22:47:45",
    "name": "Emerald Orb",
    "lang": "en-us",
    "item_type": "Weapon",
    "rank_type": "3",
    "id": "1621890360000131455"
   },
   {
    "uid": "700367142",
    "gacha_type": "200",
    "item_id": "",
    "count": "1",
    "time": "2021-05-24 22:47:39",
    "name": "Magic Guide",
    "lang": "en-us",
    "item_type": "Weapon",
    "rank_type": "3",
    "id": "1621890360000131213"
   },
   {
    "uid": "700367142",
    "gacha_type": "200",
    "item_id": "",
    "count": "1",
    "time": "2021-05-24 22:47:31",
    "name": "Thrilling Tales of Dragon Slayers",
    "lang": "en-us",
    "item_type": "Weapon",
    "rank_type": "3",
    "id": "1621890360000130959"
   }
  ]
 }
}